Workbook

Sheet BASE_CONSOLIDADA
A1: BASE_CONSOLIDADA
A2: Una fila por empleado. Fecha de referencia de permanencia: 01/09/2026. Modelo demostrativo con datos simulados.
A4: NUMERO_CEDULA | B4: NOMBRE | C4: APELLIDO | D4: EDAD | E4: GENERO | F4: CIUDAD | G4: NIVEL_EDUCATIVO | H4: ESTADO_CIVIL | I4: NUMERO_HIJOS | J4: AREA | K4: CARGO | L4: FECHA_INGRESO | M4: TIPO_CONTRATO | N4: JORNADA | O4: MODALIDAD_TRABAJO | P4: ESTADO_EMPLEADO | Q4: FECHA_RETIRO | R4: MOTIVO_RETIRO | S4: SALARIO_BASICO | T4: BONIFICACIONES | U4: HORAS_EXTRAS | V4: DEDUCCIONES | W4: SALARIO_BRUTO | X4: SALARIO_NETO | Y4: EVALUACION_DESEMPENO | Z4: SATISFACCION_LABORAL | AA4: COMPROMISO | AB4: CLIMA_LABORAL | AC4: AUSENTISMO_DIAS | AD4: INCAPACIDADES_DIAS | AE4: HORAS_CAPACITACION | AF4: NUMERO_CAPACITACIONES | AG4: PROMOCIONES | AH4: RECONOCIMIENTOS | AI4: LLAMADOS_ATENCION | AJ4: INTENCION_PERMANENCIA | AK4: FUENTE_RECLUTAMIENTO | AL4: EXPERIENCIA_ANOS | AM4: RESULTADO_ENTREVISTA | AN4: RESULTADO_PRUEBA_TECNICA | AO4: RESULTADO_PRUEBA_PSICOTECNICA | AP4: NUMERO_ENTREVISTAS | AQ4: SALARIO_INICIAL | AR4: TIEMPO_CONTRATACION_DIAS | AS4: DIAS_PERMANENCIA | AT4: MESES_PERMANENCIA | AU4: ANOS_PERMANENCIA | AV4: CATEGORIA_PERMANENCIA | AW4: ROTACION | AX4: RIESGO_ROTACION | AY4: SCORE_RIESGO
A5: =NOMINA!A5 -> 900900001 | B5: =NOMINA!B5 -> Valentina | C5: =NOMINA!C5 -> Arias | D5: =PERSONAL!E5 | E5: =PERSONAL!F5 -> F | F5: =PERSONAL!G5 -> Bogotá | G5: =PERSONAL!H5 -> Universitario | H5: =PERSONAL!I5 -> Soltero | I5: =PERSONAL!J5 -> 0 | J5: =PERSONAL!L5 -> Tecnología | K5: =PERSONAL!K5 -> Desarrollador Senior | L5: =PERSONAL!M5 -> 43143 | M5: =PERSONAL!N5 -> Indefinido | N5: =PERSONAL!O5 -> Medio tiempo | O5: =PERSONAL!P5 -> Híbrido | P5: =PERSONAL!Q5 -> RETIRADO | Q5: =PERSONAL!R5 -> 44548 | R5: =PERSONAL!S5 -> Renuncia voluntaria | S5: =NOMINA!H5 -> 7600000 | T5: =NOMINA!I5 -> 40000 | U5: =NOMINA!J5 -> 72000 | V5: =NOMINA!L5 -> 623760 | W5: =S5+T5+U5+NOMINA!K5 -> 7797000 | X5: =W5-V5 -> 7173240 | Y5: =RRHH!C5 -> 88 | Z5: =RRHH!D5 -> 5 | AA5: =RRHH!E5 -> 5 | AB5: =RRHH!F5 -> 4 | AC5: =RRHH!G5 -> 4 | AD5: =RRHH!H5 -> 2 | AE5: =RRHH!I5 -> 1 | AF5: =RRHH!J5 -> 2 | ... AI5: =RRHH!M5 -> 2 | AJ5: =RRHH!P5 -> 5 | AK5: =CONTRATACION!M5 -> LinkedIn | AL5: =CONTRATACION!N5 -> 8 | AM5: =CONTRATACION!P5 -> 90 | AN5: =CONTRATACION!Q5 -> 98.8 | AO5: =CONTRATACION!R5 -> 85 | AP5: =CONTRATACION!S5 -> 1 | AQ5: =CONTRATACION!U5 -> 7600000 | AR5: =CONTRATACION!X5 | AS5: =IF(P5="RETIRADO",Q5-L5,DATE(2026,9,1)-L5) -> 1405 | AT5: =AS5/30.4375 -> 46.160164 | AU5: =AT5/12 -> 3.8466804 | AV5: =IF(AT5<6,"Menos de 6 meses",IF(AT5<12,"6 a 12 meses",IF(AT5<24,"1 a 2 años",IF(AT5<36,"2 a 3 años",IF(AT5<60,"3 a 5 años","Más de 5 años"))))) -> 3 a 5 años | AW5: =IF(P5="RETIRADO",1,0) -> 1 | AX5: =IF(AY5>=0.67,"ALTO",IF(AY5>=0.4,"MEDIO","BAJO")) -> BAJO | AY5: =D5*0.05+(5-Z5)/5*0.25+(5-AA5)/5*0.2+(5-AB5)/5*0.15+MIN(AC5/15,1)*0.15+IF(M5="Temporal",0.12,IF(M5="Fijo",0.05,0))+(IF(X5<3000000,0.08,0)) -> 0.07
A6: =NOMINA!A6 -> 900900002 | B6: =NOMINA!B6 -> Mateo | C6: =NOMINA!C6 -> Bustos | D6: =PERSONAL!E6 | E6: =PERSONAL!F6 -> M | F6: =PERSONAL!G6 -> Medellín | G6: =PERSONAL!H6 -> Universitario | H6: =PERSONAL!I6 -> Casado | I6: =PERSONAL!J6 -> 1 | J6: =PERSONAL!L6 -> Finanzas | K6: =PERSONAL!K6 -> Analista Financiero | L6: =PERSONAL!M6 -> 43997 | M6: =PERSONAL!N6 -> Indefinido | N6: =PERSONAL!O6 -> Medio tiempo | O6: =PERSONAL!P6 -> Híbrido | P6: =PERSONAL!Q6 -> RETIRADO | Q6: =PERSONAL!R6 -> 45063 | R6: =PERSONAL!S6 -> Mejor oportunidad laboral | S6: =NOMINA!H6 -> 4300000 | T6: =NOMINA!I6 -> 20000 | U6: =NOMINA!J6 -> 30000 | V6: =NOMINA!L6 -> 375275 | W6: =S6+T6+U6+NOMINA!K6 -> 4415000 | X6: =W6-V6 -> 4039725 | Y6: =RRHH!C6 -> 83 | Z6: =RRHH!D6 -> 4 | AA6: =RRHH!E6 -> 4 | AB6: =RRHH!F6 -> 4 | AC6: =RRHH!G6 -> 3 | AD6: =RRHH!H6 -> 1 | AE6: =RRHH!I6 -> 1 | AF6: =RRHH!J6 -> 1 | ... AI6: =RRHH!M6 -> 1 | AJ6: =RRHH!P6 -> 5 | AK6: =CONTRATACION!M6 -> Referido interno | AL6: =CONTRATACION!N6 -> 4 | AM6: =CONTRATACION!P6 -> 86 | AN6: =CONTRATACION!Q6 -> 95 | AO6: =CONTRATACION!R6 -> 82 | AP6: =CONTRATACION!S6 -> 2 | AQ6: =CONTRATACION!U6 -> 4300000 | AR6: =CONTRATACION!X6 | AS6: =IF(P6="RETIRADO",Q6-L6,DATE(2026,9,1)-L6) -> 1066 | AT6: =AS6/30.4375 -> 35.022587 | AU6: =AT6/12 -> 2.9185489 | AV6: =IF(AT6<6,"Menos de 6 meses",IF(AT6<12,"6 a 12 meses",IF(AT6<24,"1 a 2 años",IF(AT6<36,"2 a 3 años",IF(AT6<60,"3 a 5 años","Más de 5 años"))))) -> 2 a 3 años | AW6: =IF(P6="RETIRADO",1,0) -> 1 | AX6: =IF(AY6>=0.67,"ALTO",IF(AY6>=0.4,"MEDIO","BAJO")) -> BAJO | AY6: =D6*0.05+(5-Z6)/5*0.25+(5-AA6)/5*0.2+(5-AB6)/5*0.15+MIN(AC6/15,1)*0.15+IF(M6="Temporal",0.12,IF(M6="Fijo",0.05,0))+(IF(X6<3000000,0.08,0)) -> 0.15
A7: =NOMINA!A7 -> 900900003 | B7: =NOMINA!B7 -> Sofía | C7: =NOMINA!C7 -> Cárdenas | D7: =PERSONAL!E7 | E7: =PERSONAL!F7 -> F | F7: =PERSONAL!G7 -> Cali | G7: =PERSONAL!H7 -> Universitario | H7: =PERSONAL!I7 -> Unión libre | I7: =PERSONAL!J7 -> 2 | J7: =PERSONAL!L7 -> Comercial | K7: =PERSONAL!K7 -> Ejecutivo Comercial | L7: =PERSONAL!M7 -> 44214 | M7: =PERSONAL!N7 -> Fijo | N7: =PERSONAL!O7 -> Medio tiempo | O7: =PERSONAL!P7 -> Presencial | P7: =PERSONAL!Q7 -> RETIRADO | Q7: =PERSONAL!R7 -> 45219 | R7: =PERSONAL!S7 -> Cambio de ciudad | S7: =NOMINA!H7 -> 3900000 | T7: =NOMINA!I7 -> 60000 | U7: =NOMINA!J7 -> 45000 | V7: =NOMINA!L7 -> 365400 | W7: =S7+T7+U7+NOMINA!K7 -> 4060000 | X7: =W7-V7 -> 3694600 | Y7: =RRHH!C7 -> 81 | Z7: =RRHH!D7 -> 4 | AA7: =RRHH!E7 -> 4 | AB7: =RRHH!F7 -> 4 | AC7: =RRHH!G7 -> 5 | AD7: =RRHH!H7 -> 2 | AE7: =RRHH!I7 -> 1 | AF7: =RRHH!J7 -> 1 | ... AI7: =RRHH!M7 -> 2 | AJ7: =RRHH!P7 -> 5 | AK7: =CONTRATACION!M7 -> Portal de empleo | AL7: =CONTRATACION!N7 -> 5 | AM7: =CONTRATACION!P7 -> 88 | AN7: =CONTRATACION!Q7 -> 94.3 | AO7: =CONTRATACION!R7 -> 84 | AP7: =CONTRATACION!S7 -> 2 | AQ7: =CONTRATACION!U7 -> 3900000 | AR7: =CONTRATACION!X7 | AS7: =IF(P7="RETIRADO",Q7-L7,DATE(2026,9,1)-L7) -> 1005 | AT7: =AS7/30.4375 -> 33.01848 | AU7: =AT7/12 -> 2.75154 | AV7: =IF(AT7<6,"Menos de 6 meses",IF(AT7<12,"6 a 12 meses",IF(AT7<24,"1 a 2 años",IF(AT7<36,"2 a 3 años",IF(AT7<60,"3 a 5 años","Más de 5 años"))))) -> 2 a 3 años | AW7: =IF(P7="RETIRADO",1,0) -> 1 | AX7: =IF(AY7>=0.67,"ALTO",IF(AY7>=0.4,"MEDIO","BAJO")) -> BAJO | AY7: =D7*0.05+(5-Z7)/5*0.25+(5-AA7)/5*0.2+(5-AB7)/5*0.15+MIN(AC7/15,1)*0.15+IF(M7="Temporal",0.12,IF(M7="Fijo",0.05,0))+(IF(X7<3000000,0.08,0)) -> 0.22
A8: =NOMINA!A8 -> 900900004 | B8: =NOMINA!B8 -> Santiago | C8: =NOMINA!C8 -> Duarte | D8: =PERSONAL!E8 -> 46 | E8: =PERSONAL!F8 -> M | F8: =PERSONAL!G8 -> Barranquilla | G8: =PERSONAL!H8 -> Universitario | H8: =PERSONAL!I8 -> Soltero | I8: =PERSONAL!J8 -> 3 | J8: =PERSONAL!L8 -> Operaciones | K8: =PERSONAL!K8 -> Coordinador de Operaciones | L8: =PERSONAL!M8 -> 42982 | M8: =PERSONAL!N8 -> Indefinido | N8: =PERSONAL!O8 -> Medio tiempo | O8: =PERSONAL!P8 -> Presencial | P8: =PERSONAL!Q8 -> RETIRADO | Q8: =PERSONAL!R8 -> 44657 | R8: =PERSONAL!S8 -> Renuncia voluntaria | S8: =NOMINA!H8 -> 5200000 | T8: =NOMINA!I8 -> 30000 | U8: =NOMINA!J8 -> 25000 | V8: =NOMINA!L8 -> 427600 | W8: =S8+T8+U8+NOMINA!K8 -> 5345000 | X8: =W8-V8 -> 4917400 | Y8: =RRHH!C8 -> 91 | Z8: =RRHH!D8 -> 5 | AA8: =RRHH!E8 -> 5 | AB8: =RRHH!F8 -> 4 | AC8: =RRHH!G8 -> 2 | AD8: =RRHH!H8 -> 1 | AE8: =RRHH!I8 -> 2 | AF8: =RRHH!J8 -> 3 | ... AI8: =RRHH!M8 -> 2 | AJ8: =RRHH!P8 -> 5 | AK8: =CONTRATACION!M8 -> Referido interno | AL8: =CONTRATACION!N8 -> 9 | AM8: =CONTRATACION!P8 -> 96 | AN8: =CONTRATACION!Q8 -> 99.8 | AO8: =CONTRATACION!R8 -> 91 | AP8: =CONTRATACION!S8 -> 2 | AQ8: =CONTRATACION!U8 -> 5200000 | AR8: =CONTRATACION!X8 -> 35 | AS8: =IF(P8="RETIRADO",Q8-L8,DATE(2026,9,1)-L8) -> 1675 | AT8: =AS8/30.4375 -> 55.030801 | AU8: =AT8/12 -> 4.5859001 | AV8: =IF(AT8<6,"Menos de 6 meses",IF(AT8<12,"6 a 12 meses",IF(AT8<24,"1 a 2 años",IF(AT8<36,"2 a 3 años",IF(AT8<60,"3 a 5 años","Más de 5 años"))))) -> 3 a 5 años | AW8: =IF(P8="RETIRADO",1,0) -> 1 | AX8: =IF(AY8>=0.67,"ALTO",IF(AY8>=0.4,"MEDIO","BAJO")) -> ALTO | AY8: =D8*0.05+(5-Z8)/5*0.25+(5-AA8)/5*0.2+(5-AB8)/5*0.15+MIN(AC8/15,1)*0.15+IF(M8="Temporal",0.12,IF(M8="Fijo",0.05,0))+(IF(X8<3000000,0.08,0)) -> 2.35
A9: =NOMINA!A9 -> 900900005 | B9: =NOMINA!B9 -> Mariana | C9: =NOMINA!C9 -> Estrada | D9: =PERSONAL!E9 -> 45 | E9: =PERSONAL!F9 -> F | F9: =PERSONAL!G9 -> Bucaramanga | G9: =PERSONAL!H9 -> Universitario | H9: =PERSONAL!I9 -> Casado | I9: =PERSONAL!J9 -> 0 | J9: =PERSONAL!L9 -> Recursos Humanos | K9: =PERSONAL!K9 -> Analista de Selección | L9: =PERSONAL!M9 -> 44641 | M9: =PERSONAL!N9 -> Fijo | N9: =PERSONAL!O9 -> Medio tiempo | O9: =PERSONAL!P9 -> Híbrido | P9: =PERSONAL!Q9 -> RETIRADO | Q9: =PERSONAL!R9 -> 45502 | R9: =PERSONAL!S9 -> Renuncia voluntaria | S9: =NOMINA!H9 -> 3600000 | T9: =NOMINA!I9 -> 40000 | U9: =NOMINA!J9 -> 18000 | V9: =NOMINA!L9 -> 314755 | W9: =S9+T9+U9+NOMINA!K9 -> 3703000 | X9: =W9-V9 -> 3388245 | Y9: =RRHH!C9 -> 87 | Z9: =RRHH!D9 -> 4 | AA9: =RRHH!E9 -> 5 | AB9: =RRHH!F9 -> 4 | AC9: =RRHH!G9 -> 3 | AD9: =RRHH!H9 -> 1 | AE9: =RRHH!I9 -> 1 | AF9: =RRHH!J9 -> 2 | ... AI9: =RRHH!M9 -> 2 | AJ9: =RRHH!P9 -> 5 | AK9: =CONTRATACION!M9 -> LinkedIn | AL9: =CONTRATACION!N9 -> 3 | AM9: =CONTRATACION!P9 -> 92 | AN9: =CONTRATACION!Q9 -> 98.5 | AO9: =CONTRATACION!R9 -> 85 | AP9: =CONTRATACION!S9 -> 1 | AQ9: =CONTRATACION!U9 -> 3600000 | AR9: =CONTRATACION!X9 -> 36 | AS9: =IF(P9="RETIRADO",Q9-L9,DATE(2026,9,1)-L9) -> 861 | AT9: =AS9/30.4375 -> 28.287474 | AU9: =AT9/12 -> 2.3572895 | AV9: =IF(AT9<6,"Menos de 6 meses",IF(AT9<12,"6 a 12 meses",IF(AT9<24,"1 a 2 años",IF(AT9<36,"2 a 3 años",IF(AT9<60,"3 a 5 años","Más de 5 años"))))) -> 2 a 3 años | AW9: =IF(P9="RETIRADO",1,0) -> 1 | AX9: =IF(AY9>=0.67,"ALTO",IF(AY9>=0.4,"MEDIO","BAJO")) -> ALTO | AY9: =D9*0.05+(5-Z9)/5*0.25+(5-AA9)/5*0.2+(5-AB9)/5*0.15+MIN(AC9/15,1)*0.15+IF(M9="Temporal",0.12,IF(M9="Fijo",0.05,0))+(IF(X9<3000000,0.08,0)) -> 2.41
A10: =NOMINA!A10 -> 900900006 | B10: =NOMINA!B10 -> Nicolás | C10: =NOMINA!C10 -> Franco | D10: =PERSONAL!E10 -> 44 | E10: =PERSONAL!F10 -> M | F10: =PERSONAL!G10 -> Bogotá | G10: =PERSONAL!H10 -> Técnico | H10: =PERSONAL!I10 -> Unión libre | I10: =PERSONAL!J10 -> 1 | J10: =PERSONAL!L10 -> Logística | K10: =PERSONAL!K10 -> Auxiliar Logístico | L10: =PERSONAL!M10 -> 45117 | M10: =PERSONAL!N10 -> Temporal | N10: =PERSONAL!O10 -> Medio tiempo | O10: =PERSONAL!P10 -> Presencial | P10: =PERSONAL!Q10 -> RETIRADO | Q10: =PERSONAL!R10 -> 45749 | R10: =PERSONAL!S10 -> Terminación de contrato | S10: =NOMINA!H10 -> 2100000 | T10: =NOMINA!I10 -> 10000 | U10: =NOMINA!J10 -> 60000 | V10: =NOMINA!L10 -> 198000 | W10: =S10+T10+U10+NOMINA!K10 -> 2200000 | X10: =W10-V10 -> 2002000 | Y10: =RRHH!C10 -> 72 | Z10: =RRHH!D10 -> 3 | AA10: =RRHH!E10 -> 3 | AB10: =RRHH!F10 -> 3 | AC10: =RRHH!G10 -> 8 | AD10: =RRHH!H10 -> 3 | AE10: =RRHH!I10 -> 0 | AF10: =RRHH!J10 -> 0 | ... AI10: =RRHH!M10 -> 1 | AJ10: =RRHH!P10 -> 4 | AK10: =CONTRATACION!M10 -> Agencia de empleo | AL10: =CONTRATACION!N10 -> 2 | AM10: =CONTRATACION!P10 -> 78 | AN10: =CONTRATACION!Q10 -> 89.2 | AO10: =CONTRATACION!R10 -> 77 | AP10: =CONTRATACION!S10 -> 2 | AQ10: =CONTRATACION!U10 -> 2100000 | AR10: =CONTRATACION!X10 -> 37 | AS10: =IF(P10="RETIRADO",Q10-L10,DATE(2026,9,1)-L10) -> 632 | AT10: =AS10/30.4375 -> 20.76386 | AU10: =AT10/12 -> 1.7303217 | AV10: =IF(AT10<6,"Menos de 6 meses",IF(AT10<12,"6 a 12 meses",IF(AT10<24,"1 a 2 años",IF(AT10<36,"2 a 3 años",IF(AT10<60,"3 a 5 años","Más de 5 años"))))) -> 1 a 2 años | AW10: =IF(P10="RETIRADO",1,0) -> 1 | AX10: =IF(AY10>=0.67,"ALTO",IF(AY10>=0.4,"MEDIO","BAJO")) -> ALTO | AY10: =D10*0.05+(5-Z10)/5*0.25+(5-AA10)/5*0.2+(5-AB10)/5*0.15+MIN(AC10/15,1)*0.15+IF(M10="Temporal",0.12,IF(M10="Fijo",0.05,0))+(IF(X10<3000000,0.08,0)) -> 2.72
A11: =NOMINA!A11 -> 900900007 | B11: =NOMINA!B11 -> Camila | C11: =NOMINA!C11 -> Gómez | D11: =PERSONAL!E11 -> 43 | E11: =PERSONAL!F11 -> F | F11: =PERSONAL!G11 -> Medellín | G11: =PERSONAL!H11 -> Universitario | H11: =PERSONAL!I11 -> Soltero | I11: =PERSONAL!J11 -> 2 | J11: =PERSONAL!L11 -> Marketing | K11: =PERSONAL!K11 -> Especialista de Marketing | L11: =PERSONAL!M11 -> 43794 | M11: =PERSONAL!N11 -> Indefinido | N11: =PERSONAL!O11 -> Medio tiempo | O11: =PERSONAL!P11 -> Remoto | P11: =PERSONAL!Q11 -> RETIRADO | Q11: =PERSONAL!R11 -> 45203 | R11: =PERSONAL!S11 -> Mejor oportunidad laboral | S11: =NOMINA!H11 -> 4800000 | T11: =NOMINA!I11 -> 50000 | U11: =NOMINA!J11 -> 20000 | V11: =NOMINA!L11 -> 394400 | W11: =S11+T11+U11+NOMINA!K11 -> 4930000 | X11: =W11-V11 -> 4535600 | Y11: =RRHH!C11 -> 93 | Z11: =RRHH!D11 -> 5 | AA11: =RRHH!E11 -> 4 | AB11: =RRHH!F11 -> 5 | AC11: =RRHH!G11 -> 2 | AD11: =RRHH!H11 -> 0 | AE11: =RRHH!I11 -> 2 | AF11: =RRHH!J11 -> 4 | ... AI11: =RRHH!M11 -> 2 | AJ11: =RRHH!P11 -> 5 | AK11: =CONTRATACION!M11 -> LinkedIn | AL11: =CONTRATACION!N11 -> 6 | AM11: =CONTRATACION!P11 -> 92 | AN11: =CONTRATACION!Q11 -> 98.5 | AO11: =CONTRATACION!R11 -> 84 | AP11: =CONTRATACION!S11 -> 2 | AQ11: =CONTRATACION!U11 -> 4800000 | AR11: =CONTRATACION!X11 -> 38 | AS11: =IF(P11="RETIRADO",Q11-L11,DATE(2026,9,1)-L11) -> 1409 | AT11: =AS11/30.4375 -> 46.291581 | AU11: =AT11/12 -> 3.8576318 | AV11: =IF(AT11<6,"Menos de 6 meses",IF(AT11<12,"6 a 12 meses",IF(AT11<24,"1 a 2 años",IF(AT11<36,"2 a 3 años",IF(AT11<60,"3 a 5 años","Más de 5 años"))))) -> 3 a 5 años | AW11: =IF(P11="RETIRADO",1,0) -> 1 | AX11: =IF(AY11>=0.67,"ALTO",IF(AY11>=0.4,"MEDIO","BAJO")) -> ALTO | AY11: =D11*0.05+(5-Z11)/5*0.25+(5-AA11)/5*0.2+(5-AB11)/5*0.15+MIN(AC11/15,1)*0.15+IF(M11="Temporal",0.12,IF(M11="Fijo",0.05,0))+(IF(X11<3000000,0.08,0)) -> 2.21
A12: =NOMINA!A12 -> 900900008 | B12: =NOMINA!B12 -> Tomás | C12: =NOMINA!C12 -> Herrera | D12: =PERSONAL!E12 -> 42 | E12: =PERSONAL!F12 -> M | F12: =PERSONAL!G12 -> Cali | G12: =PERSONAL!H12 -> Técnico | H12: =PERSONAL!I12 -> Casado | I12: =PERSONAL!J12 -> 3 | J12: =PERSONAL!L12 -> Servicio al Cliente | K12: =PERSONAL!K12 -> Agente de Servicio | L12: =PERSONAL!M12 -> 45327 | M12: =PERSONAL!N12 -> Fijo | N12: =PERSONAL!O12 -> Medio tiempo | O12: =PERSONAL!P12 -> Presencial | P12: =PERSONAL!Q12 -> RETIRADO | Q12: =PERSONAL!R12 -> 45881 | R12: =PERSONAL!S12 -> Renuncia voluntaria | S12: =NOMINA!H12 -> 2400000 | T12: =NOMINA!I12 -> 10000 | U12: =NOMINA!J12 -> 70000 | V12: =NOMINA!L12 -> 212925 | W12: =S12+T12+U12+NOMINA!K12 -> 2505000 | X12: =W12-V12 -> 2292075 | Y12: =RRHH!C12 -> 68 | Z12: =RRHH!D12 -> 3 | AA12: =RRHH!E12 -> 3 | AB12: =RRHH!F12 -> 3 | AC12: =RRHH!G12 -> 10 | AD12: =RRHH!H12 -> 4 | AE12: =RRHH!I12 -> 0 | AF12: =RRHH!J12 -> 0 | ... AI12: =RRHH!M12 -> 1 | AJ12: =RRHH!P12 -> 4 | AK12: =CONTRATACION!M12 -> Portal de empleo | AL12: =CONTRATACION!N12 -> 1 | AM12: =CONTRATACION!P12 -> 82 | AN12: =CONTRATACION!Q12 -> 87.8 | AO12: =CONTRATACION!R12 -> 81 | AP12: =CONTRATACION!S12 -> 2 | AQ12: =CONTRATACION!U12 -> 2400000 | AR12: =CONTRATACION!X12 -> 39 | AS12: =IF(P12="RETIRADO",Q12-L12,DATE(2026,9,1)-L12) -> 554 | AT12: =AS12/30.4375 -> 18.201232 | AU12: =AT12/12 -> 1.5167693 | AV12: =IF(AT12<6,"Menos de 6 meses",IF(AT12<12,"6 a 12 meses",IF(AT12<24,"1 a 2 años",IF(AT12<36,"2 a 3 años",IF(AT12<60,"3 a 5 años","Más de 5 años"))))) -> 1 a 2 años | AW12: =IF(P12="RETIRADO",1,0) -> 1 | AX12: =IF(AY12>=0.67,"ALTO",IF(AY12>=0.4,"MEDIO","BAJO")) -> ALTO | AY12: =D12*0.05+(5-Z12)/5*0.25+(5-AA12)/5*0.2+(5-AB12)/5*0.15+MIN(AC12/15,1)*0.15+IF(M12="Temporal",0.12,IF(M12="Fijo",0.05,0))+(IF(X12<3000000,0.08,0)) -> 2.57
A13: =NOMINA!A13 -> 900900009 | B13: =NOMINA!B13 -> Isabella | C13: =NOMINA!C13 -> Ibarra | D13: =PERSONAL!E13 -> 41 | E13: =PERSONAL!F13 -> F | F13: =PERSONAL!G13 -> Barranquilla | G13: =PERSONAL!H13 -> Universitario | H13: =PERSONAL!I13 -> Unión libre | I13: =PERSONAL!J13 -> 0 | J13: =PERSONAL!L13 -> Contabilidad | K13: =PERSONAL!K13 -> Contador | L13: =PERSONAL!M13 -> 42506 | M13: =PERSONAL!N13 -> Indefinido | N13: =PERSONAL!O13 -> Medio tiempo | O13: =PERSONAL!P13 -> Híbrido | P13: =PERSONAL!Q13 -> RETIRADO | Q13: =PERSONAL!R13 -> 44198 | R13: =PERSONAL!S13 -> Jubilación | S13: =NOMINA!H13 -> 6100000 | T13: =NOMINA!I13 -> 30000 | U13: =NOMINA!J13 -> 15000 | V13: =NOMINA!L13 -> 559350 | W13: =S13+T13+U13+NOMINA!K13 -> 6215000 | X13: =W13-V13 -> 5655650 | Y13: =RRHH!C13 -> 95 | Z13: =RRHH!D13 -> 5 | AA13: =RRHH!E13 -> 5 | AB13: =RRHH!F13 -> 5 | AC13: =RRHH!G13 -> 1 | AD13: =RRHH!H13 -> 0 | AE13: =RRHH!I13 -> 3 | AF13: =RRHH!J13 -> 5 | ... AI13: =RRHH!M13 -> 3 | AJ13: =RRHH!P13 -> 5 | AK13: =CONTRATACION!M13 -> Referido interno | AL13: =CONTRATACION!N13 -> 10 | AM13: =CONTRATACION!P13 -> 96 | AN13: =CONTRATACION!Q13 -> 101.2 | AO13: =CONTRATACION!R13 -> 85 | AP13: =CONTRATACION!S13 -> 1 | AQ13: =CONTRATACION!U13 -> 6100000 | AR13: =CONTRATACION!X13 -> 40 | AS13: =IF(P13="RETIRADO",Q13-L13,DATE(2026,9,1)-L13) -> 1692 | AT13: =AS13/30.4375 -> 55.589322 | AU13: =AT13/12 -> 4.6324435 | AV13: =IF(AT13<6,"Menos de 6 meses",IF(AT13<12,"6 a 12 meses",IF(AT13<24,"1 a 2 años",IF(AT13<36,"2 a 3 años",IF(AT13<60,"3 a 5 años","Más de 5 años"))))) -> 3 a 5 años | AW13: =IF(P13="RETIRADO",1,0) -> 1 | AX13: =IF(AY13>=0.67,"ALTO",IF(AY13>=0.4,"MEDIO","BAJO")) -> ALTO | AY13: =D13*0.05+(5-Z13)/5*0.25+(5-AA13)/5*0.2+(5-AB13)/5*0.15+MIN(AC13/15,1)*0.15+IF(M13="Temporal",0.12,IF(M13="Fijo",0.05,0))+(IF(X13<3000000,0.08,0)) -> 2.06
A14: =NOMINA!A14 -> 900900010 | B14: =NOMINA!B14 -> Daniel | C14: =NOMINA!C14 -> Jiménez | D14: =PERSONAL!E14 -> 40 | E14: =PERSONAL!F14 -> M | F14: =PERSONAL!G14 -> Bucaramanga | G14: =PERSONAL!H14 -> Universitario | H14: =PERSONAL!I14 -> Soltero | I14: =PERSONAL!J14 -> 1 | J14: =PERSONAL!L14 -> Compras | K14: =PERSONAL!K14 -> Analista de Compras | L14: =PERSONAL!M14 -> 44816 | M14: =PERSONAL!N14 -> Fijo | N14: =PERSONAL!O14 -> Medio tiempo | O14: =PERSONAL!P14 -> Híbrido | P14: =PERSONAL!Q14 -> RETIRADO | Q14: =PERSONAL!R14 -> 45498 | R14: =PERSONAL!S14 -> Renuncia voluntaria | S14: =NOMINA!H14 -> 3500000 | T14: =NOMINA!I14 -> 20000 | U14: =NOMINA!J14 -> 28000 | V14: =NOMINA!L14 -> 287840 | W14: =S14+T14+U14+NOMINA!K14 -> 3598000 | X14: =W14-V14 -> 3310160 | Y14: =RRHH!C14 -> 79 | Z14: =RRHH!D14 -> 4 | AA14: =RRHH!E14 -> 4 | AB14: =RRHH!F14 -> 3 | AC14: =RRHH!G14 -> 4 | AD14: =RRHH!H14 -> 2 | AE14: =RRHH!I14 -> 1 | AF14: =RRHH!J14 -> 1 | ... AI14: =RRHH!M14 -> 2 | AJ14: =RRHH!P14 -> 5 | AK14: =CONTRATACION!M14 -> Portal de empleo | AL14: =CONTRATACION!N14 -> 4 | AM14: =CONTRATACION!P14 -> 92 | AN14: =CONTRATACION!Q14 -> 93.7 | AO14: =CONTRATACION!R14 -> 82 | AP14: =CONTRATACION!S14 -> 2 | AQ14: =CONTRATACION!U14 -> 3500000 | AR14: =CONTRATACION!X14 -> 41 | AS14: =IF(P14="RETIRADO",Q14-L14,DATE(2026,9,1)-L14) -> 682 | AT14: =AS14/30.4375 -> 22.406571 | AU14: =AT14/12 -> 1.8672142 | AV14: =IF(AT14<6,"Menos de 6 meses",IF(AT14<12,"6 a 12 meses",IF(AT14<24,"1 a 2 años",IF(AT14<36,"2 a 3 años",IF(AT14<60,"3 a 5 años","Más de 5 años"))))) -> 1 a 2 años | AW14: =IF(P14="RETIRADO",1,0) -> 1 | AX14: =IF(AY14>=0.67,"ALTO",IF(AY14>=0.4,"MEDIO","BAJO")) -> ALTO | AY14: =D14*0.05+(5-Z14)/5*0.25+(5-AA14)/5*0.2+(5-AB14)/5*0.15+MIN(AC14/15,1)*0.15+IF(M14="Temporal",0.12,IF(M14="Fijo",0.05,0))+(IF(X14<3000000,0.08,0)) -> 2.24
A15: =NOMINA!A15 -> 900900011 | B15: =NOMINA!B15 -> Luciana | C15: =NOMINA!C15 -> López | D15: =PERSONAL!E15 -> 39 | E15: =PERSONAL!F15 -> F | F15: =PERSONAL!G15 -> Bogotá | G15: =PERSONAL!H15 -> Técnico | H15: =PERSONAL!I15 -> Casado | I15: =PERSONAL!J15 -> 2 | J15: =PERSONAL!L15 -> Administración | K15: =PERSONAL!K15 -> Asistente Administrativo | L15: =PERSONAL!M15 -> 45236 | M15: =PERSONAL!N15 -> Temporal | N15: =PERSONAL!O15 -> Medio tiempo | O15: =PERSONAL!P15 -> Presencial | P15: =PERSONAL!Q15 -> RETIRADO | Q15: =PERSONAL!R15 -> 45741 | R15: =PERSONAL!S15 -> Bajo desempeño | S15: =NOMINA!H15 -> 2300000 | T15: =NOMINA!I15 -> 10000 | U15: =NOMINA!J15 -> 40000 | V15: =NOMINA!L15 -> 202300 | W15: =S15+T15+U15+NOMINA!K15 -> 2380000 | X15: =W15-V15 -> 2177700 | Y15: =RRHH!C15 -> 70 | Z15: =RRHH!D15 -> 3 | AA15: =RRHH!E15 -> 3 | AB15: =RRHH!F15 -> 3 | AC15: =RRHH!G15 -> 9 | AD15: =RRHH!H15 -> 3 | AE15: =RRHH!I15 -> 0 | AF15: =RRHH!J15 -> 0 | ... AI15: =RRHH!M15 -> 1 | AJ15: =RRHH!P15 -> 4 | AK15: =CONTRATACION!M15 -> Agencia de empleo | AL15: =CONTRATACION!N15 -> 2 | AM15: =CONTRATACION!P15 -> 78 | AN15: =CONTRATACION!Q15 -> 88.5 | AO15: =CONTRATACION!R15 -> 79 | AP15: =CONTRATACION!S15 -> 2 | AQ15: =CONTRATACION!U15 -> 2300000 | AR15: =CONTRATACION!X15 -> 42 | AS15: =IF(P15="RETIRADO",Q15-L15,DATE(2026,9,1)-L15) -> 505 | AT15: =AS15/30.4375 -> 16.591376 | AU15: =AT15/12 -> 1.3826146 | AV15: =IF(AT15<6,"Menos de 6 meses",IF(AT15<12,"6 a 12 meses",IF(AT15<24,"1 a 2 años",IF(AT15<36,"2 a 3 años",IF(AT15<60,"3 a 5 años","Más de 5 años"))))) -> 1 a 2 años | AW15: =IF(P15="RETIRADO",1,0) -> 1 | AX15: =IF(AY15>=0.67,"ALTO",IF(AY15>=0.4,"MEDIO","BAJO")) -> ALTO | AY15: =D15*0.05+(5-Z15)/5*0.25+(5-AA15)/5*0.2+(5-AB15)/5*0.15+MIN(AC15/15,1)*0.15+IF(M15="Temporal",0.12,IF(M15="Fijo",0.05,0))+(IF(X15<3000000,0.08,0)) -> 2.48
A16: =NOMINA!A16 -> 900900012 | B16: =NOMINA!B16 -> Emiliano | C16: =NOMINA!C16 -> Márquez | D16: =PERSONAL!E16 -> 37 | E16: =PERSONAL!F16 -> M | F16: =PERSONAL!G16 -> Medellín | G16: =PERSONAL!H16 -> Universitario | H16: =PERSONAL!I16 -> Unión libre | I16: =PERSONAL!J16 -> 3 | J16: =PERSONAL!L16 -> Tecnología | K16: =PERSONAL!K16 -> Ingeniero de Datos | L16: =PERSONAL!M16 -> 43563 | M16: =PERSONAL!N16 -> Indefinido | N16: =PERSONAL!O16 -> Medio tiempo | O16: =PERSONAL!P16 -> Remoto | P16: =PERSONAL!Q16 -> RETIRADO | Q16: =PERSONAL!R16 -> 44942 | R16: =PERSONAL!S16 -> Renuncia voluntaria | S16: =NOMINA!H16 -> 7200000 | T16: =NOMINA!I16 -> 40000 | U16: =NOMINA!J16 -> 35000 | V16: =NOMINA!L16 -> 661950 | W16: =S16+T16+U16+NOMINA!K16 -> 7355000 | X16: =W16-V16 -> 6693050 | Y16: =RRHH!C16 -> 94 | Z16: =RRHH!D16 -> 5 | AA16: =RRHH!E16 -> 5 | AB16: =RRHH!F16 -> 5 | AC16: =RRHH!G16 -> 2 | AD16: =RRHH!H16 -> 1 | AE16: =RRHH!I16 -> 2 | AF16: =RRHH!J16 -> 4 | ... AI16: =RRHH!M16 -> 3 | AJ16: =RRHH!P16 -> 5 | AK16: =CONTRATACION!M16 -> LinkedIn | AL16: =CONTRATACION!N16 -> 7 | AM16: =CONTRATACION!P16 -> 92 | AN16: =CONTRATACION!Q16 -> 100.9 | AO16: =CONTRATACION!R16 -> 91 | AP16: =CONTRATACION!S16 -> 2 | AQ16: =CONTRATACION!U16 -> 7200000 | AR16: =CONTRATACION!X16 -> 43 | AS16: =IF(P16="RETIRADO",Q16-L16,DATE(2026,9,1)-L16) -> 1379 | AT16: =AS16/30.4375 -> 45.305955 | AU16: =AT16/12 -> 3.7754962 | AV16: =IF(AT16<6,"Menos de 6 meses",IF(AT16<12,"6 a 12 meses",IF(AT16<24,"1 a 2 años",IF(AT16<36,"2 a 3 años",IF(AT16<60,"3 a 5 años","Más de 5 años"))))) -> 3 a 5 años | AW16: =IF(P16="RETIRADO",1,0) -> 1 | AX16: =IF(AY16>=0.67,"ALTO",IF(AY16>=0.4,"MEDIO","BAJO")) -> ALTO | AY16: =D16*0.05+(5-Z16)/5*0.25+(5-AA16)/5*0.2+(5-AB16)/5*0.15+MIN(AC16/15,1)*0.15+IF(M16="Temporal",0.12,IF(M16="Fijo",0.05,0))+(IF(X16<3000000,0.08,0)) -> 1.87
... A34: =NOMINA!A34 -> 900900030 | B34: =NOMINA!B34 -> Esteban | C34: =NOMINA!C34 -> Gutiérrez | D34: =PERSONAL!E34 -> 37 | E34: =PERSONAL!F34 -> M | F34: =PERSONAL!G34 -> Bucaramanga | G34: =PERSONAL!H34 -> Universitario | H34: =PERSONAL!I34 -> Unión libre | I34: =PERSONAL!J34 -> 1 | J34: =PERSONAL!L34 -> Administración | K34: =PERSONAL!K34 -> Analista Administrativo | L34: =PERSONAL!M34 -> 44473 | M34: =PERSONAL!N34 -> Indefinido | N34: =PERSONAL!O34 -> Medio tiempo | O34: =PERSONAL!P34 -> Híbrido | P34: =PERSONAL!Q34 -> ACTIVO | Q34: =PERSONAL!R34 | R34: =PERSONAL!S34 | S34: =NOMINA!H34 -> 3600000 | T34: =NOMINA!I34 -> 20000 | U34: =NOMINA!J34 -> 20000 | V34: =NOMINA!L34 -> 331650 | W34: =S34+T34+U34+NOMINA!K34 -> 3685000 | X34: =W34-V34 -> 3353350 | Y34: =RRHH!C34 -> 83 | Z34: =RRHH!D34 -> 4 | AA34: =RRHH!E34 -> 4 | AB34: =RRHH!F34 -> 4 | AC34: =RRHH!G34 -> 3 | AD34: =RRHH!H34 -> 1 | AE34: =RRHH!I34 -> 1 | AF34: =RRHH!J34 -> 2 | ... AI34: =RRHH!M34 -> 2 | AJ34: =RRHH!P34 -> 5 | AK34: =CONTRATACION!M34 -> LinkedIn | AL34: =CONTRATACION!N34 -> 5 | AM34: =CONTRATACION!P34 -> 92 | AN34: =CONTRATACION!Q34 -> 95 | AO34: =CONTRATACION!R34 -> 82 | AP34: =CONTRATACION!S34 -> 2 | AQ34: =CONTRATACION!U34 -> 3600000 | AR34: =CONTRATACION!X34 -> 41 | AS34: =IF(P34="RETIRADO",Q34-L34,DATE(2026,9,1)-L34) -> 1793 | AT34: =AS34/30.4375 -> 58.907598 | AU34: =AT34/12 -> 4.9089665 | AV34: =IF(AT34<6,"Menos de 6 meses",IF(AT34<12,"6 a 12 meses",IF(AT34<24,"1 a 2 años",IF(AT34<36,"2 a 3 años",IF(AT34<60,"3 a 5 años","Más de 5 años"))))) -> 3 a 5 años | AW34: =IF(P34="RETIRADO",1,0) -> 0 | AX34: =IF(AY34>=0.67,"ALTO",IF(AY34>=0.4,"MEDIO","BAJO")) -> ALTO | AY34: =D34*0.05+(5-Z34)/5*0.25+(5-AA34)/5*0.2+(5-AB34)/5*0.15+MIN(AC34/15,1)*0.15+IF(M34="Temporal",0.12,IF(M34="Fijo",0.05,0))+(IF(X34<3000000,0.08,0)) -> 2

Sheet NOMINA
A1: Nómina integrada
A2: Información de origen integrada; todos los datos son ficticios.
A4: NUMERO_CEDULA | B4: NOMBRE | C4: APELLIDO | D4: CARGO | E4: AREA | F4: TIPO_CONTRATO | G4: FECHA_INGRESO | H4: SALARIO_BASICO | I4: BONIFICACIONES | J4: HORAS_EXTRAS | K4: OTROS_INGRESOS | L4: DEDUCCIONES | M4: SALARIO_BRUTO | N4: SALARIO_NETO | O4: PERIODO_NOMINA | P4: ESTADO_EMPLEADO
A5: 900900001 | B5: Valentina | C5: Arias | D5: Desarrollador Senior | E5: Tecnología | F5: Indefinido | G5: 43143 | H5: 7600000 | I5: 40000 | J5: 72000 | K5: 85000 | L5: 623760 | O5: 2026-09 | P5: RETIRADO
A6: 900900002 | B6: Mateo | C6: Bustos | D6: Analista Financiero | E6: Finanzas | F6: Indefinido | G6: 43997 | H6: 4300000 | I6: 20000 | J6: 30000 | K6: 65000 | L6: 375275 | O6: 2026-09 | P6: RETIRADO
A7: 900900003 | B7: Sofía | C7: Cárdenas | D7: Ejecutivo Comercial | E7: Comercial | F7: Fijo | G7: 44214 | H7: 3900000 | I7: 60000 | J7: 45000 | K7: 55000 | L7: 365400 | O7: 2026-09 | P7: RETIRADO
A8: 900900004 | B8: Santiago | C8: Duarte | D8: Coordinador de Operaciones | E8: Operaciones | F8: Indefinido | G8: 42982 | H8: 5200000 | I8: 30000 | J8: 25000 | K8: 90000 | L8: 427600 | M8: =H5+I5+J5+K5 -> 7797000 | N8: =M5-L5 -> -623760 | O8: 2026-09 | P8: RETIRADO
A9: 900900005 | B9: Mariana | C9: Estrada | D9: Analista de Selección | E9: Recursos Humanos | F9: Fijo | G9: 44641 | H9: 3600000 | I9: 40000 | J9: 18000 | K9: 45000 | L9: 314755 | M9: =H6+I6+J6+K6 -> 4415000 | N9: =M6-L6 -> -375275 | O9: 2026-09 | P9: RETIRADO
A10: 900900006 | B10: Nicolás | C10: Franco | D10: Auxiliar Logístico | E10: Logística | F10: Temporal | G10: 45117 | H10: 2100000 | I10: 10000 | J10: 60000 | K10: 30000 | L10: 198000 | M10: =H7+I7+J7+K7 -> 4060000 | N10: =M7-L7 -> -365400 | O10: 2026-09 | P10: RETIRADO
A11: 900900007 | B11: Camila | C11: Gómez | D11: Especialista de Marketing | E11: Marketing | F11: Indefinido | G11: 43794 | H11: 4800000 | I11: 50000 | J11: 20000 | K11: 60000 | L11: 394400 | M11: =H8+I8+J8+K8 -> 5345000 | N11: =M8-L8 -> 7369400 | O11: 2026-09 | P11: RETIRADO
A12: 900900008 | B12: Tomás | C12: Herrera | D12: Agente de Servicio | E12: Servicio al Cliente | F12: Fijo | G12: 45327 | H12: 2400000 | I12: 10000 | J12: 70000 | K12: 25000 | L12: 212925 | M12: =H9+I9+J9+K9 -> 3703000 | N12: =M9-L9 -> 4100245 | O12: 2026-09 | P12: RETIRADO
A13: 900900009 | B13: Isabella | C13: Ibarra | D13: Contador | E13: Contabilidad | F13: Indefinido | G13: 42506 | H13: 6100000 | I13: 30000 | J13: 15000 | K13: 70000 | L13: 559350 | M13: =H10+I10+J10+K10 -> 2200000 | N13: =M10-L10 -> 3862000 | O13: 2026-09 | P13: RETIRADO
A14: 900900010 | B14: Daniel | C14: Jiménez | D14: Analista de Compras | E14: Compras | F14: Fijo | G14: 44816 | H14: 3500000 | I14: 20000 | J14: 28000 | K14: 50000 | L14: 287840 | M14: =H11+I11+J11+K11 -> 4930000 | N14: =M11-L11 -> 4950600 | O14: 2026-09 | P14: RETIRADO
A15: 900900011 | B15: Luciana | C15: López | D15: Asistente Administrativo | E15: Administración | F15: Temporal | G15: 45236 | H15: 2300000 | I15: 10000 | J15: 40000 | K15: 30000 | L15: 202300 | M15: =H12+I12+J12+K12 -> 2505000 | N15: =M12-L12 -> 3490075 | O15: 2026-09 | P15: RETIRADO
A16: 900900012 | B16: Emiliano | C16: Márquez | D16: Ingeniero de Datos | E16: Tecnología | F16: Indefinido | G16: 43563 | H16: 7200000 | I16: 40000 | J16: 35000 | K16: 80000 | L16: 661950 | M16: =H13+I13+J13+K13 -> 6215000 | N16: =M13-L13 -> 1640650 | O16: 2026-09 | P16: RETIRADO
A17: 900900013 | B17: Antonia | C17: Navarro | D17: Supervisor de Planta | E17: Operaciones | F17: Indefinido | G17: 43395 | H17: 5600000 | I17: 30000 | J17: 22000 | K17: 85000 | L17: 458960 | M17: =H14+I14+J14+K14 -> 3598000 | N17: =M14-L14 -> 4642160 | O17: 2026-09 | P17: RETIRADO
A18: 900900014 | B18: Gabriel | C18: Ortega | D18: Asesor Comercial | E18: Comercial | F18: Fijo | G18: 45033 | H18: 2800000 | I18: 80000 | J18: 90000 | K18: 35000 | L18: 255425 | M18: =H15+I15+J15+K15 -> 2380000 | N18: =M15-L15 -> 2302700 | O18: 2026-09 | P18: RETIRADO
A19: 900900015 | B19: Renata | C19: Pardo | D19: Gerente Financiero | E19: Finanzas | F19: Indefinido | G19: 42023 | H19: 10500000 | I19: 60000 | J19: 10000 | K19: 120000 | L19: 962100 | M19: =H16+I16+J16+K16 -> 7355000 | N19: =M16-L16 -> 5553050 | O19: 2026-09 | P19: RETIRADO
... A34: 900900030 | B34: Esteban | C34: Gutiérrez | D34: Analista Administrativo | E34: Administración | F34: Indefinido | G34: 44473 | H34: 3600000 | I34: 20000 | J34: 20000 | K34: 45000 | L34: 331650 | M34: =H31+I31+J31+K31 -> 4005000 | N34: =M31-L31 -> 7359550 | O34: 2026-09 | P34: ACTIVO
M35: =H32+I32+J32+K32 -> 5103000 | N35: =M32-L32 -> 3081760
M36: =H33+I33+J33+K33 -> 3395000 | N36: =M33-L33 -> 2691425
M37: =H34+I34+J34+K34 -> 3685000 | N37: =M34-L34 -> 3673350

Sheet PERSONAL
A1: Personal integrado
A2: Información de origen integrada; todos los datos son ficticios.
A4: NUMERO_CEDULA | B4: NOMBRE | C4: APELLIDO | D4: FECHA_NACIMIENTO | E4: EDAD | F4: GENERO | G4: CIUDAD | H4: NIVEL_EDUCATIVO | I4: ESTADO_CIVIL | J4: NUMERO_HIJOS | K4: CARGO | L4: AREA | M4: FECHA_INGRESO | N4: TIPO_CONTRATO | O4: JORNADA | P4: MODALIDAD_TRABAJO | Q4: ESTADO_EMPLEADO | R4: FECHA_RETIRO | S4: MOTIVO_RETIRO
A5: 900900001 | B5: Valentina | C5: Arias | D5: 29221 | F5: F | G5: Bogotá | H5: Universitario | I5: Soltero | J5: 0 | K5: Desarrollador Senior | L5: Tecnología | M5: 43143 | N5: Indefinido | O5: Medio tiempo | P5: Híbrido | Q5: RETIRADO | R5: 44548 | S5: Renuncia voluntaria
A6: 900900002 | B6: Mateo | C6: Bustos | D6: 29621 | F6: M | G6: Medellín | H6: Universitario | I6: Casado | J6: 1 | K6: Analista Financiero | L6: Finanzas | M6: 43997 | N6: Indefinido | O6: Medio tiempo | P6: Híbrido | Q6: RETIRADO | R6: 45063 | S6: Mejor oportunidad laboral
A7: 900900003 | B7: Sofía | C7: Cárdenas | D7: 30017 | F7: F | G7: Cali | H7: Universitario | I7: Unión libre | J7: 2 | K7: Ejecutivo Comercial | L7: Comercial | M7: 44214 | N7: Fijo | O7: Medio tiempo | P7: Presencial | Q7: RETIRADO | R7: 45219 | S7: Cambio de ciudad
A8: 900900004 | B8: Santiago | C8: Duarte | D8: 30416 | E8: =DATEDIF(D5,DATE(2026,9,1),"Y") -> 46 | F8: M | G8: Barranquilla | H8: Universitario | I8: Soltero | J8: 3 | K8: Coordinador de Operaciones | L8: Operaciones | M8: 42982 | N8: Indefinido | O8: Medio tiempo | P8: Presencial | Q8: RETIRADO | R8: 44657 | S8: Renuncia voluntaria
A9: 900900005 | B9: Mariana | C9: Estrada | D9: 30815 | E9: =DATEDIF(D6,DATE(2026,9,1),"Y") -> 45 | F9: F | G9: Bucaramanga | H9: Universitario | I9: Casado | J9: 0 | K9: Analista de Selección | L9: Recursos Humanos | M9: 44641 | N9: Fijo | O9: Medio tiempo | P9: Híbrido | Q9: RETIRADO | R9: 45502 | S9: Renuncia voluntaria
A10: 900900006 | B10: Nicolás | C10: Franco | D10: 31214 | E10: =DATEDIF(D7,DATE(2026,9,1),"Y") -> 44 | F10: M | G10: Bogotá | H10: Técnico | I10: Unión libre | J10: 1 | K10: Auxiliar Logístico | L10: Logística | M10: 45117 | N10: Temporal | O10: Medio tiempo | P10: Presencial | Q10: RETIRADO | R10: 45749 | S10: Terminación de contrato
A11: 900900007 | B11: Camila | C11: Gómez | D11: 31612 | E11: =DATEDIF(D8,DATE(2026,9,1),"Y") -> 43 | F11: F | G11: Medellín | H11: Universitario | I11: Soltero | J11: 2 | K11: Especialista de Marketing | L11: Marketing | M11: 43794 | N11: Indefinido | O11: Medio tiempo | P11: Remoto | Q11: RETIRADO | R11: 45203 | S11: Mejor oportunidad laboral
A12: 900900008 | B12: Tomás | C12: Herrera | D12: 32011 | E12: =DATEDIF(D9,DATE(2026,9,1),"Y") -> 42 | F12: M | G12: Cali | H12: Técnico | I12: Casado | J12: 3 | K12: Agente de Servicio | L12: Servicio al Cliente | M12: 45327 | N12: Fijo | O12: Medio tiempo | P12: Presencial | Q12: RETIRADO | R12: 45881 | S12: Renuncia voluntaria
A13: 900900009 | B13: Isabella | C13: Ibarra | D13: 32411 | E13: =DATEDIF(D10,DATE(2026,9,1),"Y") -> 41 | F13: F | G13: Barranquilla | H13: Universitario | I13: Unión libre | J13: 0 | K13: Contador | L13: Contabilidad | M13: 42506 | N13: Indefinido | O13: Medio tiempo | P13: Híbrido | Q13: RETIRADO | R13: 44198 | S13: Jubilación
A14: 900900010 | B14: Daniel | C14: Jiménez | D14: 32784 | E14: =DATEDIF(D11,DATE(2026,9,1),"Y") -> 40 | F14: M | G14: Bucaramanga | H14: Universitario | I14: Soltero | J14: 1 | K14: Analista de Compras | L14: Compras | M14: 44816 | N14: Fijo | O14: Medio tiempo | P14: Híbrido | Q14: RETIRADO | R14: 45498 | S14: Renuncia voluntaria
A15: 900900011 | B15: Luciana | C15: López | D15: 33183 | E15: =DATEDIF(D12,DATE(2026,9,1),"Y") -> 39 | F15: F | G15: Bogotá | H15: Técnico | I15: Casado | J15: 2 | K15: Asistente Administrativo | L15: Administración | M15: 45236 | N15: Temporal | O15: Medio tiempo | P15: Presencial | Q15: RETIRADO | R15: 45741 | S15: Bajo desempeño
A16: 900900012 | B16: Emiliano | C16: Márquez | D16: 33581 | E16: =DATEDIF(D13,DATE(2026,9,1),"Y") -> 37 | F16: M | G16: Medellín | H16: Universitario | I16: Unión libre | J16: 3 | K16: Ingeniero de Datos | L16: Tecnología | M16: 43563 | N16: Indefinido | O16: Medio tiempo | P16: Remoto | Q16: RETIRADO | R16: 44942 | S16: Renuncia voluntaria
A17: 900900013 | B17: Antonia | C17: Navarro | D17: 33615 | E17: =DATEDIF(D14,DATE(2026,9,1),"Y") -> 36 | F17: F | G17: Cali | H17: Tecnólogo | I17: Soltero | J17: 0 | K17: Supervisor de Planta | L17: Operaciones | M17: 43395 | N17: Indefinido | O17: Medio tiempo | P17: Presencial | Q17: RETIRADO | R17: 44917 | S17: Motivos personales
A18: 900900014 | B18: Gabriel | C18: Ortega | D18: 34015 | E18: =DATEDIF(D15,DATE(2026,9,1),"Y") -> 35 | F18: M | G18: Barranquilla | H18: Técnico | I18: Casado | J18: 1 | K18: Asesor Comercial | L18: Comercial | M18: 45033 | N18: Fijo | O18: Medio tiempo | P18: Híbrido | Q18: RETIRADO | R18: 45711 | S18: Renuncia voluntaria
A19: 900900015 | B19: Renata | C19: Pardo | D19: 34411 | E19: =DATEDIF(D16,DATE(2026,9,1),"Y") -> 34 | F19: F | G19: Bucaramanga | H19: Posgrado | I19: Unión libre | J19: 2 | K19: Gerente Financiero | L19: Finanzas | M19: 42023 | N19: Indefinido | O19: Medio tiempo | P19: Híbrido | Q19: RETIRADO | R19: 44442 | S19: Jubilación
... A24: 900900020 | B24: Martín | C24: Uribe | D24: 30171 | E24: =DATEDIF(D21,DATE(2026,9,1),"Y") -> 30 | F24: M | G24: Bucaramanga | H24: Técnico | I24: Casado | J24: 3 | K24: Auxiliar Contable | L24: Contabilidad | M24: 45432 | N24: Temporal | O24: Medio tiempo | P24: Presencial | Q24: RETIRADO | R24: 45857 | S24: Terminación de contrato
A25: 900900021 | B25: Ana | C25: Vargas | D25: 30570 | E25: =DATEDIF(D22,DATE(2026,9,1),"Y") -> 46 | F25: F | G25: Bogotá | H25: Universitario | I25: Unión libre | J25: 0 | K25: Jefe Administrativo | L25: Administración | M25: 42611 | N25: Indefinido | O25: Medio tiempo | P25: Híbrido | Q25: ACTIVO
A26: 900900022 | B26: Juan | C26: Wong | D26: 30969 | E26: =DATEDIF(D23,DATE(2026,9,1),"Y") -> 45 | F26: M | G26: Medellín | H26: Tecnólogo | I26: Soltero | J26: 1 | K26: Soporte TI | L26: Tecnología | M26: 44585 | N26: Fijo | O26: Medio tiempo | P26: Híbrido | Q26: ACTIVO
A27: 900900023 | B27: Laura | C27: Zamora | D27: 31368 | E27: =DATEDIF(D24,DATE(2026,9,1),"Y") -> 44 | F27: F | G27: Cali | H27: Universitario | I27: Casado | J27: 2 | K27: Analista de Operaciones | L27: Operaciones | M27: 44172 | N27: Indefinido | O27: Medio tiempo | P27: Presencial | Q27: ACTIVO
A28: 900900024 | B28: Felipe | C28: Acosta | D28: 31766 | E28: =DATEDIF(D25,DATE(2026,9,1),"Y") -> 42 | F28: M | G28: Barranquilla | H28: Posgrado | I28: Unión libre | J28: 3 | K28: Jefe de Ventas | L28: Comercial | M28: 42898 | N28: Indefinido | O28: Medio tiempo | P28: Híbrido | Q28: ACTIVO
A29: 900900025 | B29: Natalia | C29: Beltrán | D29: 31800 | E29: =DATEDIF(D26,DATE(2026,9,1),"Y") -> 41 | F29: F | G29: Bucaramanga | H29: Universitario | I29: Soltero | J29: 0 | K29: Analista de Tesorería | L29: Finanzas | M29: 44956 | N29: Fijo | O29: Medio tiempo | P29: Híbrido | Q29: ACTIVO
A30: 900900026 | B30: David | C30: Castro | D30: 32174 | E30: =DATEDIF(D27,DATE(2026,9,1),"Y") -> 40 | F30: M | G30: Bogotá | H30: Universitario | I30: Casado | J30: 1 | K30: Diseñador Digital | L30: Marketing | M30: 45306 | N30: Temporal | O30: Medio tiempo | P30: Remoto | Q30: ACTIVO
A31: 900900027 | B31: Paula | C31: Delgado | D31: 32571 | E31: =DATEDIF(D28,DATE(2026,9,1),"Y") -> 39 | F31: F | G31: Medellín | H31: Universitario | I31: Unión libre | J31: 2 | K31: Analista de Calidad | L31: Servicio al Cliente | M31: 43696 | N31: Indefinido | O31: Medio tiempo | P31: Presencial | Q31: ACTIVO
A32: 900900028 | B32: Jorge | C32: Escobar | D32: 32970 | E32: =DATEDIF(D29,DATE(2026,9,1),"Y") -> 39 | F32: M | G32: Cali | H32: Universitario | I32: Soltero | J32: 3 | K32: Coordinador de Compras | L32: Compras | M32: 43437 | N32: Fijo | O32: Medio tiempo | P32: Híbrido | Q32: ACTIVO
A33: 900900029 | B33: Sara | C33: Fuentes | D33: 33368 | E33: =DATEDIF(D30,DATE(2026,9,1),"Y") -> 38 | F33: F | G33: Barranquilla | H33: Tecnólogo | I33: Casado | J33: 0 | K33: Analista de Inventarios | L33: Logística | M33: 44753 | N33: Fijo | O33: Medio tiempo | P33: Presencial | Q33: ACTIVO
A34: 900900030 | B34: Esteban | C34: Gutiérrez | D34: 33768 | E34: =DATEDIF(D31,DATE(2026,9,1),"Y") -> 37 | F34: M | G34: Bucaramanga | H34: Universitario | I34: Unión libre | J34: 1 | K34: Analista Administrativo | L34: Administración | M34: 44473 | N34: Indefinido | O34: Medio tiempo | P34: Híbrido | Q34: ACTIVO
E35: =DATEDIF(D32,DATE(2026,9,1),"Y") -> 36
E36: =DATEDIF(D33,DATE(2026,9,1),"Y") -> 35
E37: =DATEDIF(D34,DATE(2026,9,1),"Y") -> 34

Sheet RRHH
A1: Recursos Humanos integrado
A2: Información de origen integrada; todos los datos son ficticios.
A4: NUMERO_CEDULA | B4: FECHA_EVALUACION | C4: EVALUACION_DESEMPENO | D4: SATISFACCION_LABORAL | E4: COMPROMISO | F4: CLIMA_LABORAL | G4: AUSENTISMO_DIAS | H4: INCAPACIDADES_DIAS | I4: HORAS_CAPACITACION | J4: NUMERO_CAPACITACIONES | K4: PROMOCIONES | L4: RECONOCIMIENTOS | M4: LLAMADOS_ATENCION | N4: HORAS_TRABAJO_SEMANA | O4: MODALIDAD_TRABAJO | P4: INTENCION_PERMANENCIA | Q4: RIESGO_ROTACION | R4: OBSERVACIONES_RRHH
A5: 900900001 | B5: 44548 | C5: 88 | D5: 5 | E5: 5 | F5: 4 | G5: 4 | H5: 2 | I5: 1 | J5: 2 | K5: 0 | L5: 9 | M5: 2 | N5: 1 | O5: Híbrido | P5: 5 | S5: Observación simulada 1: seguimiento periódico.
A6: 900900002 | B6: 45063 | C6: 83 | D6: 4 | E6: 4 | F6: 4 | G6: 3 | H6: 1 | I6: 1 | J6: 1 | K6: 0 | L6: 8 | M6: 1 | N6: 1 | O6: Híbrido | P6: 5 | S6: Observación simulada 2: seguimiento periódico.
A7: 900900003 | B7: 45219 | C7: 81 | D7: 4 | E7: 4 | F7: 4 | G7: 5 | H7: 2 | I7: 1 | J7: 1 | K7: 0 | L7: 10 | M7: 2 | N7: 1 | O7: Presencial | P7: 5 | S7: Observación simulada 3: seguimiento periódico.
A8: 900900004 | B8: 44657 | C8: 91 | D8: 5 | E8: 5 | F8: 4 | G8: 2 | H8: 1 | I8: 2 | J8: 3 | K8: 0 | L8: 8 | M8: 2 | N8: 1 | O8: Presencial | P8: 5 | Q8: =IF((D5/5*0.3+E5/5*0.25+C5/100*0.2+F5/5*0.15+(1-MIN(G5/15,1))*0.1)<0.4,"ALTO",IF((D5/5*0.3+E5/5*0.25+C5/100*0.2+F5/5*0.15+(1-MIN(G5/15,1))*0.1)<0.67,"MEDIO","BAJO")) -> BAJO | R8: =IF(Q5="ALTO","Riesgo elevado por combinación de percepción, desempeño y ausentismo.",IF(Q5="MEDIO","Requiere seguimiento preventivo.","Perfil con señales favorables de permanencia.")) -> Perfil con señales favorables de permanencia. | S8: Observación simulada 4: seguimiento periódico.
A9: 900900005 | B9: 45502 | C9: 87 | D9: 4 | E9: 5 | F9: 4 | G9: 3 | H9: 1 | I9: 1 | J9: 2 | K9: 0 | L9: 8 | M9: 2 | N9: 1 | O9: Híbrido | P9: 5 | Q9: =IF((D6/5*0.3+E6/5*0.25+C6/100*0.2+F6/5*0.15+(1-MIN(G6/15,1))*0.1)<0.4,"ALTO",IF((D6/5*0.3+E6/5*0.25+C6/100*0.2+F6/5*0.15+(1-MIN(G6/15,1))*0.1)<0.67,"MEDIO","BAJO")) -> BAJO | R9: =IF(Q6="ALTO","Riesgo elevado por combinación de percepción, desempeño y ausentismo.",IF(Q6="MEDIO","Requiere seguimiento preventivo.","Perfil con señales favorables de permanencia.")) -> Perfil con señales favorables de permanencia. | S9: Observación simulada 5: seguimiento periódico.
A10: 900900006 | B10: 45749 | C10: 72 | D10: 3 | E10: 3 | F10: 3 | G10: 8 | H10: 3 | I10: 0 | J10: 0 | K10: 1 | L10: 9 | M10: 1 | N10: 2 | O10: Presencial | P10: 4 | Q10: =IF((D7/5*0.3+E7/5*0.25+C7/100*0.2+F7/5*0.15+(1-MIN(G7/15,1))*0.1)<0.4,"ALTO",IF((D7/5*0.3+E7/5*0.25+C7/100*0.2+F7/5*0.15+(1-MIN(G7/15,1))*0.1)<0.67,"MEDIO","BAJO")) -> BAJO | R10: =IF(Q7="ALTO","Riesgo elevado por combinación de percepción, desempeño y ausentismo.",IF(Q7="MEDIO","Requiere seguimiento preventivo.","Perfil con señales favorables de permanencia.")) -> Perfil con señales favorables de permanencia. | S10: Observación simulada 6: seguimiento periódico.
A11: 900900007 | B11: 45203 | C11: 93 | D11: 5 | E11: 4 | F11: 5 | G11: 2 | H11: 0 | I11: 2 | J11: 4 | K11: 0 | L11: 8 | M11: 2 | N11: 1 | O11: Remoto | P11: 5 | Q11: =IF((D8/5*0.3+E8/5*0.25+C8/100*0.2+F8/5*0.15+(1-MIN(G8/15,1))*0.1)<0.4,"ALTO",IF((D8/5*0.3+E8/5*0.25+C8/100*0.2+F8/5*0.15+(1-MIN(G8/15,1))*0.1)<0.67,"MEDIO","BAJO")) -> BAJO | R11: =IF(Q8="ALTO","Riesgo elevado por combinación de percepción, desempeño y ausentismo.",IF(Q8="MEDIO","Requiere seguimiento preventivo.","Perfil con señales favorables de permanencia.")) -> Perfil con señales favorables de permanencia. | S11: Observación simulada 7: seguimiento periódico.
A12: 900900008 | B12: 45881 | C12: 68 | D12: 3 | E12: 3 | F12: 3 | G12: 10 | H12: 4 | I12: 0 | J12: 0 | K12: 2 | L12: 9 | M12: 1 | N12: 3 | O12: Presencial | P12: 4 | Q12: =IF((D9/5*0.3+E9/5*0.25+C9/100*0.2+F9/5*0.15+(1-MIN(G9/15,1))*0.1)<0.4,"ALTO",IF((D9/5*0.3+E9/5*0.25+C9/100*0.2+F9/5*0.15+(1-MIN(G9/15,1))*0.1)<0.67,"MEDIO","BAJO")) -> BAJO | R12: =IF(Q9="ALTO","Riesgo elevado por combinación de percepción, desempeño y ausentismo.",IF(Q9="MEDIO","Requiere seguimiento preventivo.","Perfil con señales favorables de permanencia.")) -> Perfil con señales favorables de permanencia. | S12: Observación simulada 8: seguimiento periódico.
A13: 900900009 | B13: 44198 | C13: 95 | D13: 5 | E13: 5 | F13: 5 | G13: 1 | H13: 0 | I13: 3 | J13: 5 | K13: 0 | L13: 8 | M13: 3 | N13: 1 | O13: Híbrido | P13: 5 | Q13: =IF((D10/5*0.3+E10/5*0.25+C10/100*0.2+F10/5*0.15+(1-MIN(G10/15,1))*0.1)<0.4,"ALTO",IF((D10/5*0.3+E10/5*0.25+C10/100*0.2+F10/5*0.15+(1-MIN(G10/15,1))*0.1)<0.67,"MEDIO","BAJO")) -> MEDIO | R13: =IF(Q10="ALTO","Riesgo elevado por combinación de percepción, desempeño y ausentismo.",IF(Q10="MEDIO","Requiere seguimiento preventivo.","Perfil con señales favorables de permanencia.")) -> Perfil con señales favorables de permanencia. | S13: Observación simulada 9: seguimiento periódico.
A14: 900900010 | B14: 45498 | C14: 79 | D14: 4 | E14: 4 | F14: 3 | G14: 4 | H14: 2 | I14: 1 | J14: 1 | K14: 0 | L14: 8 | M14: 2 | N14: 1 | O14: Híbrido | P14: 5 | Q14: =IF((D11/5*0.3+E11/5*0.25+C11/100*0.2+F11/5*0.15+(1-MIN(G11/15,1))*0.1)<0.4,"ALTO",IF((D11/5*0.3+E11/5*0.25+C11/100*0.2+F11/5*0.15+(1-MIN(G11/15,1))*0.1)<0.67,"MEDIO","BAJO")) -> BAJO | R14: =IF(Q11="ALTO","Riesgo elevado por combinación de percepción, desempeño y ausentismo.",IF(Q11="MEDIO","Requiere seguimiento preventivo.","Perfil con señales favorables de permanencia.")) -> Perfil con señales favorables de permanencia. | S14: Observación simulada 10: seguimiento periódico.
A15: 900900011 | B15: 45741 | C15: 70 | D15: 3 | E15: 3 | F15: 3 | G15: 9 | H15: 3 | I15: 0 | J15: 0 | K15: 1 | L15: 9 | M15: 1 | N15: 2 | O15: Presencial | P15: 4 | Q15: =IF((D12/5*0.3+E12/5*0.25+C12/100*0.2+F12/5*0.15+(1-MIN(G12/15,1))*0.1)<0.4,"ALTO",IF((D12/5*0.3+E12/5*0.25+C12/100*0.2+F12/5*0.15+(1-MIN(G12/15,1))*0.1)<0.67,"MEDIO","BAJO")) -> MEDIO | R15: =IF(Q12="ALTO","Riesgo elevado por combinación de percepción, desempeño y ausentismo.",IF(Q12="MEDIO","Requiere seguimiento preventivo.","Perfil con señales favorables de permanencia.")) -> Perfil con señales favorables de permanencia. | S15: Observación simulada 11: seguimiento periódico.
A16: 900900012 | B16: 44942 | C16: 94 | D16: 5 | E16: 5 | F16: 5 | G16: 2 | H16: 1 | I16: 2 | J16: 4 | K16: 0 | L16: 8 | M16: 3 | N16: 1 | O16: Remoto | P16: 5 | Q16: =IF((D13/5*0.3+E13/5*0.25+C13/100*0.2+F13/5*0.15+(1-MIN(G13/15,1))*0.1)<0.4,"ALTO",IF((D13/5*0.3+E13/5*0.25+C13/100*0.2+F13/5*0.15+(1-MIN(G13/15,1))*0.1)<0.67,"MEDIO","BAJO")) -> BAJO | R16: =IF(Q13="ALTO","Riesgo elevado por combinación de percepción, desempeño y ausentismo.",IF(Q13="MEDIO","Requiere seguimiento preventivo.","Perfil con señales favorables de permanencia.")) -> Requiere seguimiento preventivo. | S16: Observación simulada 12: seguimiento periódico.
A17: 900900013 | B17: 44917 | C17: 86 | D17: 4 | E17: 4 | F17: 4 | G17: 3 | H17: 1 | I17: 2 | J17: 2 | K17: 0 | L17: 8 | M17: 2 | N17: 1 | O17: Presencial | P17: 5 | Q17: =IF((D14/5*0.3+E14/5*0.25+C14/100*0.2+F14/5*0.15+(1-MIN(G14/15,1))*0.1)<0.4,"ALTO",IF((D14/5*0.3+E14/5*0.25+C14/100*0.2+F14/5*0.15+(1-MIN(G14/15,1))*0.1)<0.67,"MEDIO","BAJO")) -> BAJO | R17: =IF(Q14="ALTO","Riesgo elevado por combinación de percepción, desempeño y ausentismo.",IF(Q14="MEDIO","Requiere seguimiento preventivo.","Perfil con señales favorables de permanencia.")) -> Perfil con señales favorables de permanencia. | S17: Observación simulada 13: seguimiento periódico.
A18: 900900014 | B18: 45711 | C18: 65 | D18: 3 | E18: 2 | F18: 3 | G18: 12 | H18: 4 | I18: 0 | J18: 0 | K18: 2 | L18: 10 | M18: 1 | N18: 3 | O18: Híbrido | P18: 4 | Q18: =IF((D15/5*0.3+E15/5*0.25+C15/100*0.2+F15/5*0.15+(1-MIN(G15/15,1))*0.1)<0.4,"ALTO",IF((D15/5*0.3+E15/5*0.25+C15/100*0.2+F15/5*0.15+(1-MIN(G15/15,1))*0.1)<0.67,"MEDIO","BAJO")) -> MEDIO | R18: =IF(Q15="ALTO","Riesgo elevado por combinación de percepción, desempeño y ausentismo.",IF(Q15="MEDIO","Requiere seguimiento preventivo.","Perfil con señales favorables de permanencia.")) -> Requiere seguimiento preventivo. | S18: Observación simulada 14: seguimiento periódico.
A19: 900900015 | B19: 44442 | C19: 97 | D19: 5 | E19: 5 | F19: 5 | G19: 1 | H19: 0 | I19: 4 | J19: 6 | K19: 0 | L19: 8 | M19: 3 | N19: 1 | O19: Híbrido | P19: 5 | Q19: =IF((D16/5*0.3+E16/5*0.25+C16/100*0.2+F16/5*0.15+(1-MIN(G16/15,1))*0.1)<0.4,"ALTO",IF((D16/5*0.3+E16/5*0.25+C16/100*0.2+F16/5*0.15+(1-MIN(G16/15,1))*0.1)<0.67,"MEDIO","BAJO")) -> BAJO | R19: =IF(Q16="ALTO","Riesgo elevado por combinación de percepción, desempeño y ausentismo.",IF(Q16="MEDIO","Requiere seguimiento preventivo.","Perfil con señales favorables de permanencia.")) -> Perfil con señales favorables de permanencia. | S19: Observación simulada 15: seguimiento periódico.
... A34: 900900030 | B34: 46266 | C34: 83 | D34: 4 | E34: 4 | F34: 4 | G34: 3 | H34: 1 | I34: 1 | J34: 2 | K34: 0 | L34: 8 | M34: 2 | N34: 1 | O34: Híbrido | P34: 5 | Q34: =IF((D31/5*0.3+E31/5*0.25+C31/100*0.2+F31/5*0.15+(1-MIN(G31/15,1))*0.1)<0.4,"ALTO",IF((D31/5*0.3+E31/5*0.25+C31/100*0.2+F31/5*0.15+(1-MIN(G31/15,1))*0.1)<0.67,"MEDIO","BAJO")) -> BAJO | R34: =IF(Q31="ALTO","Riesgo elevado por combinación de percepción, desempeño y ausentismo.",IF(Q31="MEDIO","Requiere seguimiento preventivo.","Perfil con señales favorables de permanencia.")) -> Perfil con señales favorables de permanencia. | S34: Observación simulada 30: seguimiento periódico.
Q35: =IF((D32/5*0.3+E32/5*0.25+C32/100*0.2+F32/5*0.15+(1-MIN(G32/15,1))*0.1)<0.4,"ALTO",IF((D32/5*0.3+E32/5*0.25+C32/100*0.2+F32/5*0.15+(1-MIN(G32/15,1))*0.1)<0.67,"MEDIO","BAJO")) -> BAJO | R35: =IF(Q32="ALTO","Riesgo elevado por combinación de percepción, desempeño y ausentismo.",IF(Q32="MEDIO","Requiere seguimiento preventivo.","Perfil con señales favorables de permanencia.")) -> Perfil con señales favorables de permanencia.
Q36: =IF((D33/5*0.3+E33/5*0.25+C33/100*0.2+F33/5*0.15+(1-MIN(G33/15,1))*0.1)<0.4,"ALTO",IF((D33/5*0.3+E33/5*0.25+C33/100*0.2+F33/5*0.15+(1-MIN(G33/15,1))*0.1)<0.67,"MEDIO","BAJO")) -> MEDIO | R36: =IF(Q33="ALTO","Riesgo elevado por combinación de percepción, desempeño y ausentismo.",IF(Q33="MEDIO","Requiere seguimiento preventivo.","Perfil con señales favorables de permanencia.")) -> Requiere seguimiento preventivo.
Q37: =IF((D34/5*0.3+E34/5*0.25+C34/100*0.2+F34/5*0.15+(1-MIN(G34/15,1))*0.1)<0.4,"ALTO",IF((D34/5*0.3+E34/5*0.25+C34/100*0.2+F34/5*0.15+(1-MIN(G34/15,1))*0.1)<0.67,"MEDIO","BAJO")) -> BAJO | R37: =IF(Q34="ALTO","Riesgo elevado por combinación de percepción, desempeño y ausentismo.",IF(Q34="MEDIO","Requiere seguimiento preventivo.","Perfil con señales favorables de permanencia.")) -> Perfil con señales favorables de permanencia.

Sheet CONTRATACION
A1: Contratación integrada
A2: Información de origen integrada; todos los datos son ficticios.
A4: NUMERO_CEDULA | B4: FECHA_SOLICITUD | C4: FECHA_PUBLICACION | D4: FECHA_POSTULACION | E4: FECHA_PRIMERA_ENTREVISTA | F4: FECHA_SEGUNDA_ENTREVISTA | G4: FECHA_PRUEBA_TECNICA | H4: FECHA_PRUEBA_PSICOTECNICA | I4: FECHA_CONTRATACION | J4: AREA | K4: CARGO | L4: VACANTE | M4: FUENTE_RECLUTAMIENTO | N4: EXPERIENCIA_ANOS | O4: NIVEL_EDUCATIVO | P4: RESULTADO_ENTREVISTA | Q4: RESULTADO_PRUEBA_TECNICA | R4: RESULTADO_PRUEBA_PSICOTECNICA | S4: NUMERO_ENTREVISTAS | T4: TIPO_CONTRATO_INICIAL | U4: SALARIO_INICIAL | V4: RECLUTADOR | W4: ESTADO_PROCESO | X4: TIEMPO_CONTRATACION_DIAS
A5: 900900001 | B5: 43108 | C5: 43111 | D5: 43115 | E5: 43118 | F5: 43122 | G5: 43125 | H5: 43127 | I5: 43143 | J5: Tecnología | K5: Desarrollador Senior | L5: Vacante Tecnología Desarrollador Senior | M5: LinkedIn | N5: 8 | O5: Universitario | P5: 90 | Q5: 98.8 | R5: 85 | S5: 1 | T5: Indefinido | U5: 7600000 | V5: Ana | W5: SELECCIONADO
A6: 900900002 | B6: 43961 | C6: 43964 | D6: 43969 | E6: 43972 | F6: 43976 | G6: 43979 | H6: 43981 | I6: 43997 | J6: Finanzas | K6: Analista Financiero | L6: Vacante Finanzas Analista Financiero | M6: Referido interno | N6: 4 | O6: Universitario | P6: 86 | Q6: 95 | R6: 82 | S6: 2 | T6: Indefinido | U6: 4300000 | V6: Bruno | W6: SELECCIONADO
A7: 900900003 | B7: 44177 | C7: 44180 | D7: 44186 | E7: 44189 | F7: 44193 | G7: 44196 | H7: 44198 | I7: 44214 | J7: Comercial | K7: Ejecutivo Comercial | L7: Vacante Comercial Ejecutivo Comercial | M7: Portal de empleo | N7: 5 | O7: Universitario | P7: 88 | Q7: 94.3 | R7: 84 | S7: 2 | T7: Fijo | U7: 3900000 | V7: Carla | W7: SELECCIONADO
A8: 900900004 | B8: 42944 | C8: 42947 | D8: 42954 | E8: 42957 | F8: 42961 | G8: 42964 | H8: 42966 | I8: 42982 | J8: Operaciones | K8: Coordinador de Operaciones | L8: Vacante Operaciones Coordinador de Operaciones | M8: Referido interno | N8: 9 | O8: Universitario | P8: 96 | Q8: 99.8 | R8: 91 | S8: 2 | T8: Indefinido | U8: 5200000 | V8: Diego | W8: SELECCIONADO | X8: =I5-B5 -> 35
A9: 900900005 | B9: 44602 | C9: 44605 | D9: 44613 | E9: 44616 | F9: 44620 | G9: 44623 | H9: 44625 | I9: 44641 | J9: Recursos Humanos | K9: Analista de Selección | L9: Vacante Recursos Humanos Analista de Selección | M9: LinkedIn | N9: 3 | O9: Universitario | P9: 92 | Q9: 98.5 | R9: 85 | S9: 1 | T9: Fijo | U9: 3600000 | V9: Ana | W9: SELECCIONADO | X9: =I6-B6 -> 36
A10: 900900006 | B10: 45077 | C10: 45080 | D10: 45084 | E10: 45087 | F10: 45091 | G10: 45094 | H10: 45096 | I10: 45117 | J10: Logística | K10: Auxiliar Logístico | L10: Vacante Logística Auxiliar Logístico | M10: Agencia de empleo | N10: 2 | O10: Técnico | P10: 78 | Q10: 89.2 | R10: 77 | S10: 2 | T10: Temporal | U10: 2100000 | V10: Bruno | W10: SELECCIONADO | X10: =I7-B7 -> 37
A11: 900900007 | B11: 43753 | C11: 43756 | D11: 43761 | E11: 43764 | F11: 43768 | G11: 43771 | H11: 43773 | I11: 43794 | J11: Marketing | K11: Especialista de Marketing | L11: Vacante Marketing Especialista de Marketing | M11: LinkedIn | N11: 6 | O11: Universitario | P11: 92 | Q11: 98.5 | R11: 84 | S11: 2 | T11: Indefinido | U11: 4800000 | V11: Carla | W11: SELECCIONADO | X11: =I8-B8 -> 38
A12: 900900008 | B12: 45285 | C12: 45288 | D12: 45294 | E12: 45297 | F12: 45301 | G12: 45304 | H12: 45306 | I12: 45327 | J12: Servicio al Cliente | K12: Agente de Servicio | L12: Vacante Servicio al Cliente Agente de Servicio | M12: Portal de empleo | N12: 1 | O12: Técnico | P12: 82 | Q12: 87.8 | R12: 81 | S12: 2 | T12: Fijo | U12: 2400000 | V12: Diego | W12: SELECCIONADO | X12: =I9-B9 -> 39
A13: 900900009 | B13: 42463 | C13: 42466 | D13: 42473 | E13: 42476 | F13: 42480 | G13: 42483 | H13: 42485 | I13: 42506 | J13: Contabilidad | K13: Contador | L13: Vacante Contabilidad Contador | M13: Referido interno | N13: 10 | O13: Universitario | P13: 96 | Q13: 101.2 | R13: 85 | S13: 1 | T13: Indefinido | U13: 6100000 | V13: Ana | W13: SELECCIONADO | X13: =I10-B10 -> 40
A14: 900900010 | B14: 44772 | C14: 44775 | D14: 44783 | E14: 44786 | F14: 44790 | G14: 44793 | H14: 44795 | I14: 44816 | J14: Compras | K14: Analista de Compras | L14: Vacante Compras Analista de Compras | M14: Portal de empleo | N14: 4 | O14: Universitario | P14: 92 | Q14: 93.7 | R14: 82 | S14: 2 | T14: Fijo | U14: 3500000 | V14: Bruno | W14: SELECCIONADO | X14: =I11-B11 -> 41
A15: 900900011 | B15: 45201 | C15: 45204 | D15: 45208 | E15: 45211 | F15: 45215 | G15: 45218 | H15: 45220 | I15: 45236 | J15: Administración | K15: Asistente Administrativo | L15: Vacante Administración Asistente Administrativo | M15: Agencia de empleo | N15: 2 | O15: Técnico | P15: 78 | Q15: 88.5 | R15: 79 | S15: 2 | T15: Temporal | U15: 2300000 | V15: Carla | W15: SELECCIONADO | X15: =I12-B12 -> 42
A16: 900900012 | B16: 43527 | C16: 43530 | D16: 43535 | E16: 43538 | F16: 43542 | G16: 43545 | H16: 43547 | I16: 43563 | J16: Tecnología | K16: Ingeniero de Datos | L16: Vacante Tecnología Ingeniero de Datos | M16: LinkedIn | N16: 7 | O16: Universitario | P16: 92 | Q16: 100.9 | R16: 91 | S16: 2 | T16: Indefinido | U16: 7200000 | V16: Diego | W16: SELECCIONADO | X16: =I13-B13 -> 43
A17: 900900013 | B17: 43358 | C17: 43361 | D17: 43367 | E17: 43370 | F17: 43374 | G17: 43377 | H17: 43379 | I17: 43395 | J17: Operaciones | K17: Supervisor de Planta | L17: Vacante Operaciones Supervisor de Planta | M17: Referido interno | N17: 8 | O17: Tecnólogo | P17: 88 | Q17: 96.1 | R17: 80 | S17: 1 | T17: Indefinido | U17: 5600000 | V17: Ana | W17: SELECCIONADO | X17: =I14-B14 -> 44
A18: 900900014 | B18: 44995 | C18: 44998 | D18: 45005 | E18: 45008 | F18: 45012 | G18: 45015 | H18: 45017 | I18: 45033 | J18: Comercial | K18: Asesor Comercial | L18: Vacante Comercial Asesor Comercial | M18: Redes sociales | N18: 3 | O18: Técnico | P18: 84 | Q18: 84.8 | R18: 72 | S18: 2 | T18: Fijo | U18: 2800000 | V18: Bruno | W18: SELECCIONADO | X18: =I15-B15 -> 35
A19: 900900015 | B19: 41984 | C19: 41987 | D19: 41995 | E19: 41998 | F19: 42002 | G19: 42005 | H19: 42007 | I19: 42023 | J19: Finanzas | K19: Gerente Financiero | L19: Vacante Finanzas Gerente Financiero | M19: Referido interno | N19: 14 | O19: Posgrado | P19: 98 | Q19: 101.9 | R19: 89 | S19: 2 | T19: Indefinido | U19: 10500000 | V19: Carla | W19: SELECCIONADO | X19: =I16-B16 -> 36
... A34: 900900030 | B34: 44429 | C34: 44432 | D34: 44440 | E34: 44443 | F34: 44447 | G34: 44450 | H34: 44452 | I34: 44473 | J34: Administración | K34: Analista Administrativo | L34: Vacante Administración Analista Administrativo | M34: LinkedIn | N34: 5 | O34: Universitario | P34: 92 | Q34: 95 | R34: 82 | S34: 2 | T34: Indefinido | U34: 3600000 | V34: Bruno | W34: SELECCIONADO | X34: =I31-B31 -> 41
X35: =I32-B32 -> 42
X36: =I33-B33 -> 43
X37: =I34-B34 -> 44

Sheet VARIABLES_MODELO
A1: VARIABLES_MODELO
A2: Variables empleadas por el modelo demostrativo interpretable.
A4: Tipo | B4: Variable | C4: Descripción | D4: Fuente | E4: Referencia | F4: Uso
A5: Variable objetivo | B5: MESES_PERMANENCIA | C5: Duración real o simulada del empleado en meses. | D5: Calculada | E5: AV en BASE_CONSOLIDADA | F5: Objetivo continuo
A6: Variable objetivo secundaria | B6: ROTACION | C6: 1 si el empleado está retirado; 0 si está activo. | D6: Calculada | E6: AY en BASE_CONSOLIDADA | F6: Objetivo binario
A7: Predictora económica | B7: SALARIO_NETO | C7: Salario después de deducciones. | D7: Nómina | E7: X en BASE_CONSOLIDADA | F7: Numérica
A8: Predictora de experiencia | B8: SATISFACCION_LABORAL | C8: Percepción de satisfacción en escala 1 a 5. | D8: RRHH | E8: Z en BASE_CONSOLIDADA | F8: Ordinal
A9: Predictora de desempeño | B9: EVALUACION_DESEMPENO | C9: Evaluación en escala 0 a 100. | D9: RRHH | E9: Y en BASE_CONSOLIDADA | F9: Numérica
A10: Predictora de carga | B10: AUSENTISMO_DIAS | C10: Días de ausencia registrados. | D10: RRHH | E10: AC en BASE_CONSOLIDADA | F10: Numérica
A11: Predictora contractual | B11: TIPO_CONTRATO | C11: Modalidad contractual. | D11: Personal | E11: M en BASE_CONSOLIDADA | F11: Categórica
A12: Predictora de selección | B12: TIEMPO_CONTRATACION_DIAS | C12: Días desde solicitud hasta contratación. | D12: Contratación | E12: AS en BASE_CONSOLIDADA | F12: Numérica
A13: Clasificación | B13: RIESGO_ROTACION | C13: BAJO, MEDIO o ALTO según score ponderado interpretable. | D13: Calculada | E13: AZ en BASE_CONSOLIDADA | F13: Categórica
A14: Índice auxiliar | B14: SCORE_RIESGO | C14: Score ponderado de señales de rotación; mayor valor implica mayor riesgo. | D14: Calculada | E14: BAZ en BASE_CONSOLIDADA | F14: Numérica

Sheet ANALISIS
A1: ANALISIS
A2: Análisis descriptivo y correlacional. Los resultados son demostrativos y no inferenciales.
A4: ANÁLISIS EXPLORATORIO | B4: RESULTADO | C4: INTERPRETACIÓN
A5: Permanencia promedio | B5: =AVERAGE(BASE_CONSOLIDADA!AT5:AT34) -> 49.103901 | C5: Duración media observada en la muestra simulada.
A6: Tasa de rotación | B6: =AVERAGE(BASE_CONSOLIDADA!AW5:AW34) -> 0.66666667 | C6: Proporción de empleados retirados en la fecha de referencia.
A7: Salario neto vs permanencia (correlación) | B7: =CORREL(BASE_CONSOLIDADA!X5:X34,BASE_CONSOLIDADA!AT5:AT34) -> 0.63024793 | C7: Asociación lineal descriptiva; no implica causalidad.
A8: Satisfacción vs permanencia (correlación) | B8: =CORREL(BASE_CONSOLIDADA!Z5:Z34,BASE_CONSOLIDADA!AT5:AT34) -> 0.59672281 | C8: Señal esperada de experiencia y permanencia.
A9: Desempeño vs permanencia (correlación) | B9: =CORREL(BASE_CONSOLIDADA!Y5:Y34,BASE_CONSOLIDADA!AT5:AT34) -> 0.64473732 | C9: Relación descriptiva en datos simulados.
A10: Ausentismo vs rotación (correlación) | B10: =CORREL(BASE_CONSOLIDADA!AC5:AC34,BASE_CONSOLIDADA!AW5:AW34) -> 0.14530513 | C10: Asociación descriptiva entre ausentismo y estado de retiro.
A11: Permanencia activos | B11: =AVERAGEIF(BASE_CONSOLIDADA!P5:P34,"ACTIVO",BASE_CONSOLIDADA!AT5:AT34) -> 71.53347 | C11: Promedio de empleados activos censurados a la fecha de referencia.
A12: Permanencia retirados | B12: =AVERAGEIF(BASE_CONSOLIDADA!P5:P34,"RETIRADO",BASE_CONSOLIDADA!AT5:AT34) -> 37.889117 | C12: Promedio de duración observada de empleados retirados.
A14: RESUMEN POR ÁREA | B14: EMPLEADOS | C14: PERMANENCIA PROMEDIO | D14: ROTACIÓN | E14: RIESGO ALTO
A15: Administración | B15: =COUNTIF(BASE_CONSOLIDADA!J5:J34,A12) -> 0 | C15: =AVERAGEIF(BASE_CONSOLIDADA!J5:J34,A12,BASE_CONSOLIDADA!AT5:AT34) -> #DIV/0! | D15: =AVERAGEIF(BASE_CONSOLIDADA!J5:J34,A12,BASE_CONSOLIDADA!AW5:AW34) -> #DIV/0! | E15: =COUNTIFS(BASE_CONSOLIDADA!J5:J34,A12,BASE_CONSOLIDADA!AX5:AX34,"ALTO") -> 0
A16: Comercial | B16: =COUNTIF(BASE_CONSOLIDADA!J5:J34,A13) -> 0 | C16: =AVERAGEIF(BASE_CONSOLIDADA!J5:J34,A13,BASE_CONSOLIDADA!AT5:AT34) -> #DIV/0! | D16: =AVERAGEIF(BASE_CONSOLIDADA!J5:J34,A13,BASE_CONSOLIDADA!AW5:AW34) -> #DIV/0! | E16: =COUNTIFS(BASE_CONSOLIDADA!J5:J34,A13,BASE_CONSOLIDADA!AX5:AX34,"ALTO") -> 0
A17: Compras | B17: =COUNTIF(BASE_CONSOLIDADA!J5:J34,A14) -> 0 | C17: =AVERAGEIF(BASE_CONSOLIDADA!J5:J34,A14,BASE_CONSOLIDADA!AT5:AT34) -> #DIV/0! | D17: =AVERAGEIF(BASE_CONSOLIDADA!J5:J34,A14,BASE_CONSOLIDADA!AW5:AW34) -> #DIV/0! | E17: =COUNTIFS(BASE_CONSOLIDADA!J5:J34,A14,BASE_CONSOLIDADA!AX5:AX34,"ALTO") -> 0
A18: Contabilidad | B18: =COUNTIF(BASE_CONSOLIDADA!J5:J34,A15) -> 3 | C18: =AVERAGEIF(BASE_CONSOLIDADA!J5:J34,A15,BASE_CONSOLIDADA!AT5:AT34) -> 65.193703 | D18: =AVERAGEIF(BASE_CONSOLIDADA!J5:J34,A15,BASE_CONSOLIDADA!AW5:AW34) -> 0.33333333 | E18: =COUNTIFS(BASE_CONSOLIDADA!J5:J34,A15,BASE_CONSOLIDADA!AX5:AX34,"ALTO") -> 3
A19: Finanzas | B19: =COUNTIF(BASE_CONSOLIDADA!J5:J34,A16) -> 3 | C19: =AVERAGEIF(BASE_CONSOLIDADA!J5:J34,A16,BASE_CONSOLIDADA!AT5:AT34) -> 55.315537 | D19: =AVERAGEIF(BASE_CONSOLIDADA!J5:J34,A16,BASE_CONSOLIDADA!AW5:AW34) -> 0.66666667 | E19: =COUNTIFS(BASE_CONSOLIDADA!J5:J34,A16,BASE_CONSOLIDADA!AX5:AX34,"ALTO") -> 2
A20: Logística | B20: =COUNTIF(BASE_CONSOLIDADA!J5:J34,A17) -> 2 | C20: =AVERAGEIF(BASE_CONSOLIDADA!J5:J34,A17,BASE_CONSOLIDADA!AT5:AT34) -> 57.675565 | D20: =AVERAGEIF(BASE_CONSOLIDADA!J5:J34,A17,BASE_CONSOLIDADA!AW5:AW34) -> 0.5 | E20: =COUNTIFS(BASE_CONSOLIDADA!J5:J34,A17,BASE_CONSOLIDADA!AX5:AX34,"ALTO") -> 2
A21: Marketing | B21: =COUNTIF(BASE_CONSOLIDADA!J5:J34,A18) -> 2 | C21: =AVERAGEIF(BASE_CONSOLIDADA!J5:J34,A18,BASE_CONSOLIDADA!AT5:AT34) -> 34.776181 | D21: =AVERAGEIF(BASE_CONSOLIDADA!J5:J34,A18,BASE_CONSOLIDADA!AW5:AW34) -> 1 | E21: =COUNTIFS(BASE_CONSOLIDADA!J5:J34,A18,BASE_CONSOLIDADA!AX5:AX34,"ALTO") -> 2
A22: Operaciones | B22: =COUNTIF(BASE_CONSOLIDADA!J5:J34,A19) -> 3 | C22: =AVERAGEIF(BASE_CONSOLIDADA!J5:J34,A19,BASE_CONSOLIDADA!AT5:AT34) -> 52.511978 | D22: =AVERAGEIF(BASE_CONSOLIDADA!J5:J34,A19,BASE_CONSOLIDADA!AW5:AW34) -> 0.66666667 | E22: =COUNTIFS(BASE_CONSOLIDADA!J5:J34,A19,BASE_CONSOLIDADA!AX5:AX34,"ALTO") -> 2
A23: Recursos Humanos | B23: =COUNTIF(BASE_CONSOLIDADA!J5:J34,A20) -> 3 | C23: =AVERAGEIF(BASE_CONSOLIDADA!J5:J34,A20,BASE_CONSOLIDADA!AT5:AT34) -> 37.69473 | D23: =AVERAGEIF(BASE_CONSOLIDADA!J5:J34,A20,BASE_CONSOLIDADA!AW5:AW34) -> 0.66666667 | E23: =COUNTIFS(BASE_CONSOLIDADA!J5:J34,A20,BASE_CONSOLIDADA!AX5:AX34,"ALTO") -> 3
A24: Servicio al Cliente | B24: =COUNTIF(BASE_CONSOLIDADA!J5:J34,A21) -> 3 | C24: =AVERAGEIF(BASE_CONSOLIDADA!J5:J34,A21,BASE_CONSOLIDADA!AT5:AT34) -> 35.263518 | D24: =AVERAGEIF(BASE_CONSOLIDADA!J5:J34,A21,BASE_CONSOLIDADA!AW5:AW34) -> 0.66666667 | E24: =COUNTIFS(BASE_CONSOLIDADA!J5:J34,A21,BASE_CONSOLIDADA!AX5:AX34,"ALTO") -> 3
A25: Tecnología | B25: =COUNTIF(BASE_CONSOLIDADA!J5:J34,A22) -> 3 | C25: =AVERAGEIF(BASE_CONSOLIDADA!J5:J34,A22,BASE_CONSOLIDADA!AT5:AT34) -> 57.943874 | D25: =AVERAGEIF(BASE_CONSOLIDADA!J5:J34,A22,BASE_CONSOLIDADA!AW5:AW34) -> 0.66666667 | E25: =COUNTIFS(BASE_CONSOLIDADA!J5:J34,A22,BASE_CONSOLIDADA!AX5:AX34,"ALTO") -> 3
A27: RESUMEN POR CONTRATO | B27: EMPLEADOS | C27: PERMANENCIA PROMEDIO | D27: ROTACIÓN
A28: Indefinido | B28: =COUNTIF(BASE_CONSOLIDADA!M5:M34,A25) -> 0 | C28: =AVERAGEIF(BASE_CONSOLIDADA!M5:M34,A25,BASE_CONSOLIDADA!AT5:AT34) -> #DIV/0! | D28: =AVERAGEIF(BASE_CONSOLIDADA!M5:M34,A25,BASE_CONSOLIDADA!AW5:AW34) -> #DIV/0!
A29: Fijo | B29: =COUNTIF(BASE_CONSOLIDADA!M5:M34,A26) -> 0 | C29: =AVERAGEIF(BASE_CONSOLIDADA!M5:M34,A26,BASE_CONSOLIDADA!AT5:AT34) -> #DIV/0! | D29: =AVERAGEIF(BASE_CONSOLIDADA!M5:M34,A26,BASE_CONSOLIDADA!AW5:AW34) -> #DIV/0!
A30: Temporal | B30: =COUNTIF(BASE_CONSOLIDADA!M5:M34,A27) -> 0 | C30: =AVERAGEIF(BASE_CONSOLIDADA!M5:M34,A27,BASE_CONSOLIDADA!AT5:AT34) -> #DIV/0! | D30: =AVERAGEIF(BASE_CONSOLIDADA!M5:M34,A27,BASE_CONSOLIDADA!AW5:AW34) -> #DIV/0!

Sheet SIMULADOR
A1: SIMULADOR DE PERMANENCIA
A2: Ingrese o modifique los valores amarillos. Resultado: modelo demostrativo basado en datos simulados.
E4: Permanencia estimada (meses) | F4: =MAX(1,ROUND(12+F5*0.5+B12*0.12+B13*0.18+B14*0.1+B6*0.7+B10*3+B11*1.5-IF(B9<3,8,0)-IF(B8="Temporal",10,IF(B8="Fijo",4,0))-B15*0.8,0)) -> #VALUE! | G4: Estimación heurística interpretable.
A5: Campo | B5: Valor | C5: Notas | E5: Permanencia estimada (años) | F5: =MAX(1,ROUND(12+B10*0.5+B12*1.8+B13*2+B14*0.1+B8/1000000*0.8+B16*0.05-IF(B12<3,8,0)-IF(B9="Temporal",10,IF(B9="Fijo",4,0))-B15*0.8,0)) -> #VALUE! | G5: Conversión de meses a años.
A6: Edad | B6: 30 | C6: Años | E6: Score de riesgo | F6: =F5/12 -> #VALUE! | G6: Mayor valor equivale a mayor riesgo.
A7: Área | B7: Tecnología | C7: Lista de áreas simuladas | E7: Riesgo de rotación | F7: =MAX(0,MIN(1,0.7-(B12/5*0.2)-(B13/5*0.16)-(B14/100*0.14)+MIN(B15/15,1)*0.16+IF(B9="Temporal",0.14,IF(B9="Fijo",0.06,0)))) -> #VALUE! | G7: Clasificación por umbrales.
A8: Cargo | B8: Analista | C8: Texto libre | E8: Factores de mayor influencia | F8: =IF(F7>=0.67,"ALTO",IF(F7>=0.4,"MEDIO","BAJO")) -> #VALUE! | G8: Lectura cualitativa del resultado.
A9: Salario mensual | B9: 4500000 | C9: Pesos colombianos simulados | F9: =IF(F8="ALTO","Satisfacción/compromiso bajos, ausentismo alto o contrato temporal",IF(F8="MEDIO","Revisar satisfacción, contrato y ausentismo","Señales favorables: satisfacción, desempeño y contrato")) -> #VALUE!
A10: Tipo de contrato | B10: Indefinido | C10: Indefinido / Fijo / Temporal
A11: Experiencia previa | B11: 5 | C11: Años
A12: Nivel educativo | B12: Universitario | C12: Técnico / Tecnólogo / Universitario / Posgrado | E12: ESCENARIOS WHAT-IF
A13: Satisfacción esperada | B13: 4 | C13: Escala 1 a 5 | E13: Escenario | F13: Descripción | G13: Permanencia (meses) | H13: Riesgo
A14: Compromiso esperado | B14: 4 | C14: Escala 1 a 5 | E14: A | F14: Salario bajo + satisfacción baja | G14: =MAX(1,ROUND(12+4*0.5+2*1.8+3*2+70*0.1+2500000/1000000*0.8+20*0.05-IF(2<3,8,0)-IF("Temporal"="Temporal",10,IF("Temporal"="Fijo",4,0))-IF("A"="E",12,0),0)) -> 16 | H14: =IF((0.7-(2/5*0.2)-(3/5*0.16)-(70/100*0.14)+IF("A"="E",0.16,0)+IF("Temporal"="Temporal",0.14,IF("Temporal"="Fijo",0.06,0)))>=0.67,"ALTO",IF((0.7-(2/5*0.2)-(3/5*0.16)-(70/100*0.14)+IF("A"="E",0.16,0)+IF("Temporal"="Temporal",0.14,IF("Temporal"="Fijo",0.06,0)))>=0.4,"MEDIO","BAJO")) -> MEDIO
A15: Desempeño esperado | B15: 82 | C15: Escala 0 a 100 | E15: B | F15: Salario competitivo + satisfacción alta | G15: =MAX(1,ROUND(12+4*0.5+5*1.8+5*2+90*0.1+6500000/1000000*0.8+20*0.05-IF(5<3,8,0)-IF("Indefinido"="Temporal",10,IF("Indefinido"="Fijo",4,0))-IF("B"="E",12,0),0)) -> 48 | H15: =IF((0.7-(5/5*0.2)-(5/5*0.16)-(90/100*0.14)+IF("B"="E",0.16,0)+IF("Indefinido"="Temporal",0.14,IF("Indefinido"="Fijo",0.06,0)))>=0.67,"ALTO",IF((0.7-(5/5*0.2)-(5/5*0.16)-(90/100*0.14)+IF("B"="E",0.16,0)+IF("Indefinido"="Temporal",0.14,IF("Indefinido"="Fijo",0.06,0)))>=0.4,"MEDIO","BAJO")) -> BAJO
A16: Ausentismo esperado | B16: 3 | C16: Días | E16: C | F16: Contrato temporal | G16: =MAX(1,ROUND(12+4*0.5+3*1.8+3*2+78*0.1+3500000/1000000*0.8+20*0.05-IF(3<3,8,0)-IF("Temporal"="Temporal",10,IF("Temporal"="Fijo",4,0))-IF("C"="E",12,0),0)) -> 27 | H16: =IF((0.7-(3/5*0.2)-(3/5*0.16)-(78/100*0.14)+IF("C"="E",0.16,0)+IF("Temporal"="Temporal",0.14,IF("Temporal"="Fijo",0.06,0)))>=0.67,"ALTO",IF((0.7-(3/5*0.2)-(3/5*0.16)-(78/100*0.14)+IF("C"="E",0.16,0)+IF("Temporal"="Temporal",0.14,IF("Temporal"="Fijo",0.06,0)))>=0.4,"MEDIO","BAJO")) -> MEDIO
A17: Horas de capacitación | B17: 20 | C17: Horas | E17: D | F17: Alto desempeño y satisfacción | G17: =MAX(1,ROUND(12+4*0.5+5*1.8+5*2+95*0.1+5000000/1000000*0.8+20*0.05-IF(5<3,8,0)-IF("Indefinido"="Temporal",10,IF("Indefinido"="Fijo",4,0))-IF("D"="E",12,0),0)) -> 48 | H17: =IF((0.7-(5/5*0.2)-(5/5*0.16)-(95/100*0.14)+IF("D"="E",0.16,0)+IF("Indefinido"="Temporal",0.14,IF("Indefinido"="Fijo",0.06,0)))>=0.67,"ALTO",IF((0.7-(5/5*0.2)-(5/5*0.16)-(95/100*0.14)+IF("D"="E",0.16,0)+IF("Indefinido"="Temporal",0.14,IF("Indefinido"="Fijo",0.06,0)))>=0.4,"MEDIO","BAJO")) -> BAJO
A18: Resultado entrevista | B18: 82 | C18: Puntaje 0 a 100 | E18: E | F18: Alto ausentismo | G18: =MAX(1,ROUND(12+4*0.5+4*1.8+4*2+82*0.1+4500000/1000000*0.8+20*0.05-IF(4<3,8,0)-IF("Indefinido"="Temporal",10,IF("Indefinido"="Fijo",4,0))-IF("E"="E",12,0),0)) -> 30 | H18: =IF((0.7-(4/5*0.2)-(4/5*0.16)-(82/100*0.14)+IF("E"="E",0.16,0)+IF("Indefinido"="Temporal",0.14,IF("Indefinido"="Fijo",0.06,0)))>=0.67,"ALTO",IF((0.7-(4/5*0.2)-(4/5*0.16)-(82/100*0.14)+IF("E"="E",0.16,0)+IF("Indefinido"="Temporal",0.14,IF("Indefinido"="Fijo",0.06,0)))>=0.4,"MEDIO","BAJO")) -> MEDIO
A19: Resultado prueba técnica | B19: 80 | C19: Puntaje 0 a 100
A20: Resultado psicotécnico | B20: 84 | C20: Puntaje 0 a 100
A21: Fuente de reclutamiento | B21: LinkedIn | C21: Fuente
A22: Modalidad de trabajo | B22: Híbrido | C22: Presencial / Híbrido / Remoto

Sheet DASHBOARD
A1: DASHBOARD | PEOPLE ANALYTICS
A2: Panel ejecutivo — todos los resultados son demostrativos y basados en datos simulados. No usar para decisiones automatizadas.
A5: Total empleados | E5: Activos | I5: Retirados
A6: =COUNTA(BASE_CONSOLIDADA!A5:A34) -> 30 | E6: =COUNTIF(BASE_CONSOLIDADA!P5:P34,"ACTIVO") -> 10 | I6: =COUNTIF(BASE_CONSOLIDADA!P5:P34,"RETIRADO") -> 20
A8: Tasa de rotación | E8: Permanencia promedio | I8: Salario promedio
A9: =AVERAGE(BASE_CONSOLIDADA!AW5:AW34) -> 0.66666667 | E9: =AVERAGE(BASE_CONSOLIDADA!AT5:AT34) -> 49.103901 | I9: =AVERAGE(BASE_CONSOLIDADA!X5:X34) -> 4259160.5
A11: Satisfacción promedio | E11: Desempeño promedio | I11: Riesgo alto
A12: =AVERAGE(BASE_CONSOLIDADA!Z5:Z34) -> 4.0666667 | E12: =AVERAGE(BASE_CONSOLIDADA!Y5:Y34) -> 82.533333 | I12: =COUNTIF(BASE_CONSOLIDADA!AX5:AX34,"ALTO") -> 27
A17: Área | B17: Empleados | C17: Permanencia promedio | D17: Rotación
A18: Administración | B18: =COUNTIF(BASE_CONSOLIDADA!J5:J34,A18) -> 3 | C18: =AVERAGEIF(BASE_CONSOLIDADA!J5:J34,A18,BASE_CONSOLIDADA!AT5:AT34) -> 65.193703 | D18: =AVERAGEIF(BASE_CONSOLIDADA!J5:J34,A18,BASE_CONSOLIDADA!AW5:AW34) -> 0.33333333
A19: Comercial | B19: =COUNTIF(BASE_CONSOLIDADA!J5:J34,A19) -> 3 | C19: =AVERAGEIF(BASE_CONSOLIDADA!J5:J34,A19,BASE_CONSOLIDADA!AT5:AT34) -> 55.315537 | D19: =AVERAGEIF(BASE_CONSOLIDADA!J5:J34,A19,BASE_CONSOLIDADA!AW5:AW34) -> 0.66666667
A20: Compras | B20: =COUNTIF(BASE_CONSOLIDADA!J5:J34,A20) -> 2 | C20: =AVERAGEIF(BASE_CONSOLIDADA!J5:J34,A20,BASE_CONSOLIDADA!AT5:AT34) -> 57.675565 | D20: =AVERAGEIF(BASE_CONSOLIDADA!J5:J34,A20,BASE_CONSOLIDADA!AW5:AW34) -> 0.5
A21: Contabilidad | B21: =COUNTIF(BASE_CONSOLIDADA!J5:J34,A21) -> 2 | C21: =AVERAGEIF(BASE_CONSOLIDADA!J5:J34,A21,BASE_CONSOLIDADA!AT5:AT34) -> 34.776181 | D21: =AVERAGEIF(BASE_CONSOLIDADA!J5:J34,A21,BASE_CONSOLIDADA!AW5:AW34) -> 1
A22: Finanzas | B22: =COUNTIF(BASE_CONSOLIDADA!J5:J34,A22) -> 3 | C22: =AVERAGEIF(BASE_CONSOLIDADA!J5:J34,A22,BASE_CONSOLIDADA!AT5:AT34) -> 52.511978 | D22: =AVERAGEIF(BASE_CONSOLIDADA!J5:J34,A22,BASE_CONSOLIDADA!AW5:AW34) -> 0.66666667
A23: Logística | B23: =COUNTIF(BASE_CONSOLIDADA!J5:J34,A23) -> 3 | C23: =AVERAGEIF(BASE_CONSOLIDADA!J5:J34,A23,BASE_CONSOLIDADA!AT5:AT34) -> 37.69473 | D23: =AVERAGEIF(BASE_CONSOLIDADA!J5:J34,A23,BASE_CONSOLIDADA!AW5:AW34) -> 0.66666667
A24: Marketing | B24: =COUNTIF(BASE_CONSOLIDADA!J5:J34,A24) -> 3 | C24: =AVERAGEIF(BASE_CONSOLIDADA!J5:J34,A24,BASE_CONSOLIDADA!AT5:AT34) -> 35.263518 | D24: =AVERAGEIF(BASE_CONSOLIDADA!J5:J34,A24,BASE_CONSOLIDADA!AW5:AW34) -> 0.66666667
A25: Operaciones | B25: =COUNTIF(BASE_CONSOLIDADA!J5:J34,A25) -> 3 | C25: =AVERAGEIF(BASE_CONSOLIDADA!J5:J34,A25,BASE_CONSOLIDADA!AT5:AT34) -> 57.943874 | D25: =AVERAGEIF(BASE_CONSOLIDADA!J5:J34,A25,BASE_CONSOLIDADA!AW5:AW34) -> 0.66666667
A26: Recursos Humanos | B26: =COUNTIF(BASE_CONSOLIDADA!J5:J34,A26) -> 2 | C26: =AVERAGEIF(BASE_CONSOLIDADA!J5:J34,A26,BASE_CONSOLIDADA!AT5:AT34) -> 42.036961 | D26: =AVERAGEIF(BASE_CONSOLIDADA!J5:J34,A26,BASE_CONSOLIDADA!AW5:AW34) -> 1
A27: Servicio al Cliente | B27: =COUNTIF(BASE_CONSOLIDADA!J5:J34,A27) -> 3 | C27: =AVERAGEIF(BASE_CONSOLIDADA!J5:J34,A27,BASE_CONSOLIDADA!AT5:AT34) -> 48.558522 | D27: =AVERAGEIF(BASE_CONSOLIDADA!J5:J34,A27,BASE_CONSOLIDADA!AW5:AW34) -> 0.66666667
A28: Tecnología | B28: =COUNTIF(BASE_CONSOLIDADA!J5:J34,A28) -> 3 | C28: =AVERAGEIF(BASE_CONSOLIDADA!J5:J34,A28,BASE_CONSOLIDADA!AT5:AT34) -> 48.898015 | D28: =AVERAGEIF(BASE_CONSOLIDADA!J5:J34,A28,BASE_CONSOLIDADA!AW5:AW34) -> 0.66666667
A31: Contrato | B31: Permanencia promedio
A32: Indefinido | B32: =AVERAGEIF(BASE_CONSOLIDADA!M5:M34,A32,BASE_CONSOLIDADA!AT5:AT34) -> 62.633265
A33: Fijo | B33: =AVERAGEIF(BASE_CONSOLIDADA!M5:M34,A33,BASE_CONSOLIDADA!AT5:AT34) -> 40.978159
A34: Temporal | B34: =AVERAGEIF(BASE_CONSOLIDADA!M5:M34,A34,BASE_CONSOLIDADA!AT5:AT34) -> 20.714579
A37: Riesgo | B37: Empleados
A38: BAJO | B38: =COUNTIF(BASE_CONSOLIDADA!AX5:AX34,A38) -> 3
A39: MEDIO | B39: =COUNTIF(BASE_CONSOLIDADA!AX5:AX34,A39) -> 0
A40: ALTO | B40: =COUNTIF(BASE_CONSOLIDADA!AX5:AX34,A40) -> 27
A45: CONCLUSIÓN EJECUTIVA
A46: Los hallazgos se calculan mediante fórmulas en el libro y deben interpretarse como demostrativos. La permanencia, rotación y asociaciones por salario, satisfacción, desempeño, ausentismo y contrato sirven para ilustrar el flujo de People Analytics, no para inferir relaciones causales ni tomar decisiones sobre personas. El perfil de mayor riesgo combina señales de satisfacción/compromiso más bajas, mayor ausentismo y contrato menos estable. En un entorno real se necesitarían más observaciones, datos reales gobernados, validación estadística, evaluación de sesgos y controles de privacidad.

Sheet DICCIONARIO_DATOS
A1: DICCIONARIO_DATOS
A2: Definiciones y uso de las variables del prototipo.
A4: Variable | B4: Descripción | C4: Fuente | D4: Tipo de dato | E4: Valores permitidos | F4: Original/calculada | G4: Fórmula | H4: Utilidad para el modelo
A5: NUMERO_CEDULA | B5: Variable de nómina | C5: NOMINA | D5: Texto/numérico | E5: Según catálogo | F5: Original | H5: Condición económica
A6: NOMBRE | B6: Variable de nómina | C6: NOMINA | D6: Texto/numérico | E6: Según catálogo | F6: Original | H6: Condición económica
A7: APELLIDO | B7: Variable de nómina | C7: NOMINA | D7: Texto/numérico | E7: Según catálogo | F7: Original | H7: Condición económica
A8: CARGO | B8: Variable de nómina | C8: NOMINA | D8: Texto/numérico | E8: Según catálogo | F8: Original | H8: Condición económica
A9: AREA | B9: Variable de nómina | C9: NOMINA | D9: Texto/numérico | E9: Según catálogo | F9: Original | H9: Condición económica
A10: TIPO_CONTRATO | B10: Variable de nómina | C10: NOMINA | D10: Texto/numérico | E10: Según catálogo | F10: Original | H10: Condición económica
A11: FECHA_INGRESO | B11: Variable de nómina | C11: NOMINA | D11: Texto/numérico | E11: Según catálogo | F11: Original | H11: Condición económica
A12: SALARIO_BASICO | B12: Variable de nómina | C12: NOMINA | D12: Texto/numérico | E12: Según catálogo | F12: Original | H12: Condición económica
A13: BONIFICACIONES | B13: Variable de nómina | C13: NOMINA | D13: Texto/numérico | E13: Según catálogo | F13: Original | H13: Condición económica
A14: HORAS_EXTRAS | B14: Variable de nómina | C14: NOMINA | D14: Texto/numérico | E14: Según catálogo | F14: Original | H14: Condición económica
A15: OTROS_INGRESOS | B15: Variable de nómina | C15: NOMINA | D15: Texto/numérico | E15: Según catálogo | F15: Original | H15: Condición económica
A16: DEDUCCIONES | B16: Variable de nómina | C16: NOMINA | D16: Texto/numérico | E16: Según catálogo | F16: Original | H16: Condición económica
... A81: TIEMPO_CONTRATACION_DIAS | B81: Variable del proceso de contratación | C81: CONTRATACION | D81: Texto/numérico/fecha | E81: Según catálogo | F81: Calculada | H81: Calidad del proceso de selección
A82: DIAS_PERMANENCIA | B82: Variable analítica del modelo | C82: BASE_CONSOLIDADA | D82: Numérico/texto | E82: Definido en metodología | F82: Calculada | G82: Ver METODOLOGIA | H82: Objetivo o predictor
A83: MESES_PERMANENCIA | B83: Variable analítica del modelo | C83: BASE_CONSOLIDADA | D83: Numérico/texto | E83: Definido en metodología | F83: Calculada | G83: Ver METODOLOGIA | H83: Objetivo o predictor
A84: ANOS_PERMANENCIA | B84: Variable analítica del modelo | C84: BASE_CONSOLIDADA | D84: Numérico/texto | E84: Definido en metodología | F84: Calculada | G84: Ver METODOLOGIA | H84: Objetivo o predictor
A85: CATEGORIA_PERMANENCIA | B85: Variable analítica del modelo | C85: BASE_CONSOLIDADA | D85: Numérico/texto | E85: Definido en metodología | F85: Calculada | G85: Ver METODOLOGIA | H85: Objetivo o predictor
A86: ROTACION | B86: Variable analítica del modelo | C86: BASE_CONSOLIDADA | D86: Numérico/texto | E86: Definido en metodología | F86: Calculada | G86: Ver METODOLOGIA | H86: Objetivo o predictor
A87: RIESGO_ROTACION | B87: Variable analítica del modelo | C87: BASE_CONSOLIDADA | D87: Numérico/texto | E87: Definido en metodología | F87: Calculada | G87: Ver METODOLOGIA | H87: Objetivo o predictor
A88: SCORE_RIESGO | B88: Variable analítica del modelo | C88: BASE_CONSOLIDADA | D88: Numérico/texto | E88: Definido en metodología | F88: Calculada | G88: Ver METODOLOGIA | H88: Objetivo o predictor

Sheet METODOLOGIA
A1: METODOLOGIA
A2: Documentación técnica, supuestos, interpretación y advertencia de uso.
A4: Tema | B4: Descripción
A5: Propósito | B5: Prototipo académico de People Analytics para integrar contratación, personal, nómina y RRHH, calcular permanencia y demostrar un esquema interpretable de riesgo de rotación.
A6: Naturaleza de los datos | B6: Todos los datos, nombres, identificaciones, fechas, salarios y resultados son completamente ficticios y fueron construidos para simulación.
A7: Cobertura | B7: 30 empleados únicos; los mismos NUMERO_CEDULA aparecen en NOMINA, PERSONAL, RRHH y CONTRATACION. Se incluyen empleados activos y retirados, múltiples áreas, cargos y contratos.
A8: Llave de integración | B8: NUMERO_CEDULA es la llave única común a las cuatro bases. La BASE_CONSOLIDADA contiene una fila por empleado.
A9: Fecha de referencia | B9: 01/09/2026. Para activos, permanencia = fecha de referencia - fecha de ingreso. Para retirados, permanencia = fecha de retiro - fecha de ingreso.
A10: Permanencia | B10: DIAS_PERMANENCIA se convierte a MESES_PERMANENCIA dividiendo por 30.4375; ANOS_PERMANENCIA = meses / 12. CATEGORIA_PERMANENCIA usa seis intervalos.
A11: Rotación | B11: ROTACION = 1 para RETIRADO y 0 para ACTIVO. Esta definición es demostrativa y no pretende representar un evento de supervivencia plenamente observado.
A12: Riesgo | B12: SCORE_RIESGO combina satisfacción, compromiso, desempeño, ausentismo, tipo de contrato y salario. RIESGO_ROTACION: BAJO < 0.40; MEDIO entre 0.40 y <0.67; ALTO >=0.67. Mayor score = mayor riesgo.
A13: Modelo demostrativo | B13: Se utiliza una fórmula heurística ponderada e interpretable, apropiada para mostrar el funcionamiento con 30 observaciones. No se presenta como predicción real ni se usa para decisiones automatizadas.
A14: Simulador | B14: La hoja SIMULADOR permite modificar inputs en amarillo y calcula permanencia estimada, años, score, riesgo y factores cualitativos. Incluye cinco escenarios What-if.
A15: Análisis | B15: Se presentan promedios, tasas, correlaciones descriptivas y agrupaciones por área/contrato. Las asociaciones no prueban causalidad.
... A17: Advertencia obligatoria | B17: Este sistema constituye un prototipo académico de People Analytics desarrollado con datos completamente simulados. Los resultados del modelo son demostrativos y no representan predicciones reales. El modelo no debe utilizarse para tomar decisiones automatizadas de contratación, despido, promoción o permanencia de personas. En un entorno empresarial real sería necesario utilizar datos reales, mayor cantidad de observaciones, validación estadística, evaluación de sesgos, controles de privacidad y validación del modelo antes de cualquier uso operativo.

Sheet CONTROL_CALIDAD
A1: CONTROL_CALIDAD
A2: Validaciones automáticas; se espera que las comprobaciones críticas presenten OK.
A4: VALIDACIÓN | B4: RESULTADO | C4: DETALLE
A5: Mínimo 20 empleados únicos | B5: =IF(COUNTA(BASE_CONSOLIDADA!A5:A34)>=20,"OK","ERROR") -> OK | C5: Debe haber al menos 20 cédulas.
A6: Cédulas duplicadas en consolidada | B6: {=IF(SUMPRODUCT((COUNTIF(BASE_CONSOLIDADA!A5:A34,BASE_CONSOLIDADA!A5:A34)>1)*1)=0,"OK","ERROR")} -> OK | C6: Una fila por empleado.
A7: Mismos empleados en las cuatro bases | B7: =IF(AND(COUNTA(NOMINA!A2:A31)=COUNTA(PERSONAL!A2:A31),COUNTA(NOMINA!A2:A31)=COUNTA(RRHH!A2:A31),COUNTA(NOMINA!A2:A31)=COUNTA(CONTRATACION!A2:A31)),"OK","ERROR") -> OK | C7: Conteos consistentes.
A8: Activos y retirados | B8: =IF(AND(COUNTIF(BASE_CONSOLIDADA!P5:P34,"ACTIVO")>0,COUNTIF(BASE_CONSOLIDADA!P5:P34,"RETIRADO")>0),"OK","ERROR") -> OK | C8: Se requiere mezcla de estados.
A9: Fechas de retiro coherentes | B9: =IF(SUMPRODUCT(--(BASE_CONSOLIDADA!P5:P34="RETIRADO"),--(BASE_CONSOLIDADA!Q5:Q34<=BASE_CONSOLIDADA!L5:L34))=0,"OK","ERROR") -> OK | C9: Retiro posterior a ingreso.
A10: Activos sin fecha de retiro | B10: =IF(COUNTIFS(BASE_CONSOLIDADA!P5:P34,"ACTIVO",BASE_CONSOLIDADA!Q5:Q34,"<>0")=0,"OK","ERROR") -> OK | C10: Activos deben tener fecha vacía.
A11: Retirados con fecha de retiro | B11: =IF(COUNTIFS(BASE_CONSOLIDADA!P5:P34,"RETIRADO",BASE_CONSOLIDADA!Q5:Q34,"=0")=0,"OK","ERROR") -> OK | C11: Retirados deben tener fecha.
A12: Salarios no negativos | B12: =IF(MIN(BASE_CONSOLIDADA!S5:S34)>=0,"OK","ERROR") -> OK | C12: Salarios simulados no negativos.
A13: Resultados dentro de rango | B13: =IF(AND(MIN(BASE_CONSOLIDADA!Y5:Y34)>=0,MAX(BASE_CONSOLIDADA!Y5:Y34)<=100,MIN(BASE_CONSOLIDADA!Z5:AB34)>=1,MAX(BASE_CONSOLIDADA!Z5:AB34)<=5),"OK","ERROR") -> OK | C13: Escalas de desempeño y percepción.
A14: Salario bruto correcto | B14: =IF(SUMPRODUCT(--(ABS(BASE_CONSOLIDADA!W5:W34-(BASE_CONSOLIDADA!S5:S34+BASE_CONSOLIDADA!T5:T34+BASE_CONSOLIDADA!U5:U34+NOMINA!K5:K34))<0.01))=30,"OK","ERROR") -> OK | C14: Bruto = básico + bonificaciones + horas extras + otros ingresos.
A15: Salario neto correcto | B15: =IF(SUMPRODUCT(--(ABS(BASE_CONSOLIDADA!X5:X34-(BASE_CONSOLIDADA!W5:W34-BASE_CONSOLIDADA!V5:V34))<0.01))=30,"OK","ERROR") -> OK | C15: Neto = bruto - deducciones.
A16: Tiempo de contratación correcto | B16: =IF(SUMPRODUCT(--(BASE_CONSOLIDADA!AS5:AS34>=0))=30,"OK","ERROR") -> OK | C16: Contratación posterior a solicitud.
A17: Permanencia no negativa | B17: =IF(MIN(BASE_CONSOLIDADA!AS5:AS34)>=0,"OK","ERROR") -> OK | C17: Duración coherente.
A18: Cédulas faltantes | B18: =IF(COUNTBLANK(BASE_CONSOLIDADA!A5:A34)=0,"OK","ERROR") -> OK | C18: Todas las filas tienen llave.
